{
  "book": "Zohar",
  "parsha": "Vayechi",
  "segments": [
    {
      "id": "Zohar_Vayechi.1.1",
      "book": "Zohar",
      "parsha": "Vayechi",
      "chapter": 1,
      "text_en": "\"And Jacob lived in the land of Egypt seventeen years\" (Beresheet 47:28). Rabbi Yosi said, Jacob's heart saw through prophecy in Egypt that his descendants would suffer many exiles - from then until now, until the End, and the time of the Coming of Messiah. Jacob arrived at the prophecy of \"and...lived\" only in Egypt. It was an excellent prophecy, the like of which was never prophesied before. None of the prophets was worthy of it except for him and Moses. It is written of Moses, \"For no man shall see Me, and live\" (Shemot 33:20). Of Jacob, it is written, \"And Jacob lived\", the prophecy which descends from the shining mirror. Jacob wanted to prophesy concerning the exiles of his children in the land of Canaan and in any land wherein they dwelt which came from the land of Egypt; to wit, all exiles are included within Egypt. His heart broke, as it is written, \"Now Jacob saw that there was corn (also: 'breaking') in Egypt\" (Beresheet 42:1). Hence, when it came to pass that \"Jacob lived in Egypt,\" he did not rejoice, because this land was the bond of the nations; the sapphires of the Throne of Glory. Nobody came to them, neither from the upper nor from the lower, save the living. This is the secret of: \"For no man shall see Me, and live.\" There are high mysteries in this verse, and we friends wonder about them, for it says that Jacob lived instead of Yisrael, to wit 'And Israel lived.' For the name Jacob indicates smallness, and the name Israel indicates Mochin of greatness, while \"and lived\" alludes to the Light of Chayah, which is the Mochin of greatness. It should have said, 'And Israel lived.' How do we know that Yisrael indicates Mochin of Greatness? From the verse, \"Yisrael is holy to Hashem\" (Jer. 2:3), (Holy is an allusion to greatness). It also says, \"Israel is My son, My firstborn\" (Shemot 4:22), firstborn being an allusion to greatness. Rabbi Elazar, the son of Rabbi Shimon, said, Yet scripture says, \"and he sold his birthright to Jacob\" (Beresheet 25:33), for with the birthright, which is greatness, the name Jacob is mentioned. His father Rabbi Shimon said to him: When Yisrael were righteous men of truth and gave charity, they were not afraid, save Jacob alone, due to the good deeds Yisrael did, and the kindness amongst them.",
      "text_he": "וַיְחִי יַעֲקֹב בְּאֶרֶץ מִצְרַיִם שְׁבַע עֶשְׂרֵה שָׁנָה וגו'. אָמַר רִבִּי יוֹסֵי, לִבָּא חָמָא בִּנְבוּאָה, בְּמִצְרַיִם, דִּיהוֹן בְּנוֹהִי בְּכַמָּה גַּלָּוון, עַד הָכָא ועַד עִדָּנָא דְּקֵץ מְשִׁיחָא. ולָא מָטָא לִנְבוּאָה דְּויְחִי אֶלָּא בְּמִצְרַיִם. וְהִיא מַעַלְיָיתָא, נְבוּאָתָא מִדְּאִתְנַבִּיאוּ (ד\"א לא אתנביאו) אִתְנַבִּיאוּ דְּכַוָּותָה, וְלָא מָטָא לְהוּ שׁוּם אֵינִישׁ מִן בְּנִי נְבִיאָה, אֶלָּא הוּא וּמשֶׁה. בְּמשֶׁה כְּתִיב, (שמות ל״ג:כ׳) כִּי לא יִרְאַנִי הָאָדָם וָחָי. בְּיַעֲקֹב כְּתִיב, ויְחִי יַעֲקֹב. וַיְחִי, נְבוּאָתָה דְּנַחֲתָא מֵאַסְפַּקְלַרְיָאה (מאירתא) דְּנַהֲרָא. בָּעֵי לְמֵימַר (חפץ ההוא הוה בעינוהי) נְבוּאָן דְּגָלוּתָא דְּעַרְעָן לִבְנוֹהִי בְּאַרְעָא דִכְנָעַן וּבְכָל אַרְעָא דְאִתּוֹתַב בָּהּ. מֵאַרְעָא דְמִצְרַיִם הֲוָה תְּבִיר לִבֵּיהּ. דִּכְתִיב, (בראשית מ״ב:א׳) כִּי יֵשׁ שֶׁבֶר בְּמִצְרַיִם. וְעַל דָּא מָטָא, וַיְחִי יַעֲקֹב בְּמִצְרַיִם, וְלָא הֲוָה חָדֵי. (סי א') כִּי בְּאַרְעָא הַהִיא סְפֵיקָן דְּעַמִין, סַפִּרִין דְּכוּרְסֵי יְקָרָא. וְלָא מָטָא לְהוֹן שׁוּם אֵינִישׁ, לָא מִן עִלָּאָה וְלָא מִן תַּתָּאָה, אֶלָּא ח\"י. וְרָזָא דָא, כִּי לֹא יִרְאַנִי הָאָדָם וָחָי. כַּמָּה הוּא רָזָא עִלָּאָה בְּדָא קְרָא, וְאֲנַן חַבְרַיָיא תְּמֵיהִין עֲלַיְיהוּ, עַל וַיְחִי דְּדָכִיר עִמֵּיהּ יַעֲקֹב. הֲוָה לֵיהּ לְמֵימַר קַמֵּי יִשְׂרָאֵל. יִשְׂרָאֵל מִנַּיִן, דִּכְתִיב, (ירמיהו ב׳:ג׳) קֹדֶשׁ יִשְׂרָאֵל לַה' רֵאשִׁית וְגו'. (שמות ד) בְּנִי בְּכוֹרִי יִשְׂרָאֵל. רִבִּי אֶלְעָזָר בְּרֵיהּ דְּרִבִּי שִׁמְעוֹן אָמַר, וְכִי לָא אָמַר קְרָא, (בראשית כ״ה:ל״ג) וַיִּמְכֹּר אֶת בְּכוֹרָתוֹ לְיַעֲקֹב. אָמַר רִבִּי שִׁמְעוֹן אֲבוּהָ, בְּעִידְנָא דְּהֲווּ יִשְׂרָאֵל קְשִׁיטִין וְזַכָּאִין וְעָבְדִין זְכוּ, וְלָא הֲווּ רְתִיתִין יִשְׂרָאֵל, אֶלָּא יַעֲקֹב לְחוּדֵיהּ. בְּדִין טָבָאן דְּעָבְדִין, הֲוָה לְמֶעְבַּד לְהוּ טָבָאן סַגִּיאִין דָּא בְּדָא. מִדְּחָבוּ, וְאִתְגְּלִיאוּ עַל חוֹבֵיהוֹן, וְעַל עוֹבָדֵיהוֹן בִּישִׁין, לָא הֲווּ סָבְלִין יָתֵיהּ, דְּלָא יֶהֶוְיָין לְעַלְמָא, בְּקוּשְׁטָא עַל חוֹבֵיהוֹן. וְעַל דָּא אָתֵי מְכִילְתָּא דְרַחֲמֵי וְדִינָא לְחוּד, יִשְׂרָאֵל, וְיַהֲבִית (וישראל יהבית) יַתְהוֹן בְּאַרְעָא גָּלוּתְהוֹן. יָאוֹת בָּעֵי בְּרִי, אֲבָל אִינִישׁ מִסְתַּכֵּל וְיִנְדַע יָתֵיהּ, יַעֲקֹב דְּמִתְלַף עִם וַיְחִי, קֹדֶשׁ. וְעַל דְּנָא רָזָא אָמְרִין, יַעֲקֹב בָּחַר יָתֵיהּ סַפִּירָא בְּכוּרְסֵי יְקָרָא. רִבִּי שִׁמְעוֹן פָּתַח וְאָמַר, (ישעיהו נ״ז:ט״ו) וְאֶת דַּכָּא וּשְׁפַל רוּחַ לְהַחֲיוֹת רוּחַ שְׁפָלִים וּלְהַחֲיוֹת לֵב נִדְכָּאִים. לֵב נִדְכָּאִים, דָּא יַעֲקֹב. כְּמָא דְאַתְּ אָמֵר, תְּחוֹת מִן דַּרְגָּא נְחִיתַת עֲלוֹהִי נְבִיאִין בִּרְכָאן בְּמִצְרַיִם. תָּנָא אָמַר רִבִּי אַבָּא, לִבָּא חָמָא, דְּיַעֲקֹב דְּהֲוָה בְּמִצְרַיִם לֵית נְבוּאָתֵיהּ מַעַלְיוּתָא. (ס\"א דארעא סניאה) אַרְעָא סַגִּיאָה. תָּא חֲזֵי, לָא זָכֵי לְבָרֵךְ לְחַד מִבְּנוֹהִי, וְלָא הֲוָה בִּידֵיהּ רוּחָא לְבָרֵךְ אֶלָּא בְּמִצְרַיִם, כַּד בָּרִיךְ יַתְהוֹן כָּל חַד וְחַד בְּרָזָא. וְרָזָא (בראשית מ״ב:א׳) וַיַּרְא יַעֲקֹב כִּי יֵשׁ שֶׁבֶר בְּמִצְרַיִם וַיֹּאמֶר יַעֲקֹב לְבָנָיו לָמָּה תִּתְרָאוּ. תָּא חֲזֵי, דְּלָא אִיתְיְיהִיבַת נְבוּאֲתָא, אֶלָּא לִתְבִירֵי לִבָּא. כְּמָא דְאַתְּ אָמֵר, (בראשית מ״ב:ב׳) רְדוּ שָׁמָּה וְשִׁבְרוּ לָנוּ מִשָּׁם וְנִחְיֶה וְלֹא נָמוּת. אָמַר רִבִּי יוֹסֵי, תְּחוֹת כָּרְסֵי יְקָרָא קַדִּישָׁא, יַעֲקֹב סַפִּיר, דְּאִיהִי מְכִילָתָא דְּדִינָא לְסִטְרֵיהּ, אֲתָא אָמַר, (בראשית ל״ב:כ״ט) לֹא יַעֲקֹב יֵאָמֵר עוֹד שִׁמְּךָ כִּי אִם יִשְׂרָאֵל כִּי שָׂרִיתָ עִם אֱלֹהִים וְעִם אֲנָשִׁים וַתּוּכָל. אַתְּ מַשְׁכַּח דְּיַעֲקֹב חָזָא לְסִטְרֵיהּ מְכִילָתָא דְּדִינָא, וַיִּזְרַח לוֹ הַשֶּׁמֶשׁ כַּאֲשֶׁר עָבַר אֶת פְּנוּאֵל וְגו', וְרָזָא דְמִלָּה (ירמיהו ו׳:ד׳) אוֹי לָנוּ כִּי פָנָה הַיּוֹם כִּי יִנָּטוּ צִלְּלֵי עָרֶב. רִבִּי שִׁמְעוֹן אָמַר, כַּד אִתְגְּלִיאוּ מִן יְרוּשְׁלֵם, וְאַעֲדִיאוּ תְּדִירָא, וְסָאִיב מְסַנְאָה יַת הֵיכָלָא. בְּעִדָּנָא הַהִיא לָא סוֹבְלַת מַלְכוּתָא לְיִשְׂרָאֵל עַל חוֹבֵיהוֹן, אֶלָּא יִשְׂרָאֵל. בְּגִין דְּהִיא מִתְּרֵי גִיסָא, רַחֲמֵי וְדִינָא. וּמִלָּה דְּלֹא יַעֲקֹב יֵאָמֵר עוֹד שִׁמְךָ כִּי אִם יִשְׂרָאֵל, כַּד אִתְפְּרִישׁ בִּסְבִירֵיהּ. יִשְׂרָאֵל יַעֲקֹב עִלָּאָה דָּא מִן דָּא, וּבְגִינֵהוֹן הֲוָה חוּטְרָא דְמשֶׁה גְּלִיפָא מִתְּרֵין סִטְרוֹי מִשְׁמֵיהּ קַדִּישָׁא, חַד רַחֲמֵי בְּדִינָא, וְחַד דִּינָא בְּדִינָא. וְרָזָא (במדבר כ״ג:כ״א) לֹא הִבִּיט אָוֶן בְּיַעֲקֹב וְלא רָאָה עָמָל בְּיִשְׂרָאֵל, מִדַּאֲנַן בְּגָלוּתָא, דְּחִיקָן בֵּין שָׂנְאֵי, וְאִסְתַּלִּיקַת מַטְרוֹנִיתָא מִן מַלְכָּא, וְאִתְרְחִיקַת מִנֵּיהּ, הוּא יַשְׁרֵי שְׁכִינְתָּא בֵּינָנָא וְיִפְרְקִינָנָא. וְרָזָא (ישעיהו מ״ה:י״ג) כֹּה אָמַר ה' מֶלֶךְ יִשְׂרָאֵל וְגוֹאֲלוֹ ה' צְבָאוֹת. וַיְחִי חַי, (ישעיהו ס״ו:א׳) כֹּה אָמַר ה' הַשָּׁמַיִם כִּסְאִי וְהָאָרֶץ הֲדוֹם רַגְלָי. בִּנְיָן עִלָּאָה, שְׁתֵּ\"י רַגְלַי חַי, לי' רַבָּתָא, י' לְח' זְעֵירְתָּא, ח' לְתיו, וי' לְו', ו' לְד', הֲדָא הוּא דְּנָפִיק מֵעִלָּאָה. תְּחוֹת כָּרְסֵיהּ יְקָרָא, מֵאֶבֶן טָבָא בְּאֶרֶץ מִצְרַיִם. הַיְינוּ דִּכְתִיב, (ישעיהו י״ט:כ״ב) וְנָגַף ה' אֶת מִצְרַיִם וְגו', י\"ב פְּרִישָׁא. (ישעיהו כ״ו:י״ט) כִּי טַל אוֹרוֹת טַלֶּךָ א' בְּגִין פְּרִישָׁא. וּבְגִין דָּא מִתְחַלַף כְּחֲדָא, ב' פְּרִישָׁא גָּלוּתָא, א' פְּרִישָׁא קַדְמַיְיתָא. תָּא חֲזֵי, מַאי דִכְתִיב, (ישעיהו ב׳:ה׳) בֵּית יַעֲקֹב לְכוּ וְנֵלְכָה בְּאוֹר ה', בְּגָלוּתָא, אַתְוָון דְּאִתְגְּזַר עֲלֵיהוֹן, עַל חוֹבֵיהוֹן, בְּקוּשְׁטָא בְּדִינָא הֲווּ, בְּאוֹרַיְיתָא תַּקַּנְתָּא, וְתִפְקוּן מִן חַמְרָא טִינָא, דְּהִיא גָלוּתָא, וְתַהֲכוּ לְנַהֲרָא דַּיְיָ. א' רְצוֹנוֹ לוֹמַר בָּאָרֶץ, אִתְצַפֵּי אֲתָא בְּתִיגְנָא דְּסִיפְרָא דְאוֹרַיְיתָא. וְאֲנָא אִתְפַּלִיג בָּאָרֶץ, בָּאָרֶץ אַתְּ מַשְׁכַּח בְּתִיגְנָא דְסִפְרָא דְאוֹרַיְיתָא, ר\"ץ מִתְלַפִּין כְּחֲדָא גָּלוּתָא. מַאי גָּלוּתָא דְמִצְרָאֵי. אַרְבַּע מְאָה שְׁנִין הֲוָה אָמַר לְאַבְרָהָם, דִּיהֵא גָּלוּתָא לִבְנוֹהִי בְּמִצְרָאֵי, וְכִי הֲוֵית מָנֵיתָא יַתְהוֹן, מָאתָן וְתִשְׁעִין שְׁנִין הֲווּ. תָּא חֲזֵי, וַיָּמָת יוֹסֵף בֶּן מֵאָה וְעֶשֶׂר שָׁנִים. רִבִּי שִׁמְעוֹן פָּתַח וְאָמַר, (ישעיה ו) הִנֵּה הָעַלְמָה הָרָה וְיוֹלֶדֶת בֵּן וְקָרָאת שְׁמוֹ עִמָּנוּאֵל, עִדּוּי וְלֵידָה, דְּאִתְמְלֵי לְגִלּוּיָאן וְעָקְתָן סַגִּיאִין וְעִידָן בִּישִׁין. וְאַף עַל גַּב דִּיְהוּ בְּאִלֵּין, מַטְרוּנִיתָא אִזְדַּעְזְעַת וְאִתְרַחֲקַת מִן בַּעֲלָהּ, תְּהֵא עִמָּנָא בְּגָלוּתָא, בֶּן מֵאָה וְעֶשֶׂר הֲוָה גִּלּוּפָא דְּאִתּוֹסַף, יִתְרְעֵי לְמֵימַר וְהֲוָה עָבַר מִן גָּלוּתָא מֵאָה וְעֶשֶׂר שְׁנִין, וּמָאתָן וְתִשְׁעִין, הֲוִי אַרְבַּע מְאָה שְׁנִין, וְלָא אִתְמְנֵי גָלוּתָא דְיַעֲקֹב, אֶלָּא מִדְּמִית יוֹסֵף, (והיינו דא על גבי דא דאמר ומעת הוסר התמיד ולתת שקוץ שומם וגו'.) וַיְּהִי יְמֵי יַעֲקֹב שְׁנֵי חַיָּיו שֶׁבַע שָׁנִים וְאַרְבָּעִים וּמְאַת שְׁנָה, הָכָא רָזָא בְּגָלוּתָא בְּמִנְיְינָא, תִּקוּנְתָּא יְהוֹן בְּנַיָיא דְּאִתְגַּלְּיָין בְּמִכִילָתָא דְּדִינָא תְּלָתָא גַּלָּוָון. קַדְמָאָה דְמִצְרָאֵי, דְּאִתְמְתַל בִּשְׁבַע שְׁנִין. רִבִּי חִיָּיא פָּתַח וְאָמַר, (שיר השירים ב׳:ז׳) הִשְׁבַּעְתִּי אֶתְכֶם בְּנוֹת יְרוּשָׁלַם בִּצְבָאוֹת אוֹ בְּאַיְלוֹת וְגו'. רִבִּי שִׁמְעוֹן אָמַר מֵהָכָא, (ירמיהו ל״א:ג׳) מֵרָחוֹק ה' נִרְאָה לִי וְאַהֲבַת עוֹלָם אֲהַבְתִּיךְ וְגו'. הָכָא רָזָא בְּגָלוּתָא תַּקַּנְתָּא יְהוֹן בְּנוֹהִי דְיִשְׂרָאֵל. מִשְׁתְּרֵי גַּלָּיָיא וְיִתְרְעֵי לְמֵימַר, יְהוֹן בְּנַיָא קַדִּישָׁא דְּאִתְגַּלָּוָון עַל חוֹבֵיהוֹן בְּדִינָא, שְׁנִין סַגִּיאִין יְהֵא. (ויקרא כ״ו:כ״א) שֶׁבַע כְּחַטֹּאתֵיכֶם, (בראשית ד׳:כ״ד) כִּי שִׁבְעָתַיִם יוּקַּם קָיִן, בְּגָלוּתָא קַדְמָאָה דְמִצְרָאֵי, דְּהִיא זְעֵירָא. תִּנְיָינָא, גָּלוּתָא דְשׁוֹפְטִים, דְּאִתְמְתַל לְאַרְבָּעִים שְׁנִין, בִּשְׁבַע דְּאִינְהוּ סַגִּיאֵי מִנֵּיהּ. תְּלִיתָאֵי, גָּלוּתָא דַאֲנַן בֵּיהּ אֲרִיכָא, דְּאִתְמְתַל לִמְאָה שְׁנִין, לְאַרְבְּעִין וְהַיְינוּ דָּא עַל גַּבֵּי עִלָאָה דְּאֲמָר (דניאל י״ב:י״א) וּמֵעֵת הוּסַר הַתָּמִיד וְלָתֵת שִׁקּוּץ שׁוֹמֵם וְגו':"
    },
    {
      "id": "Zohar_Vayechi.16.1",
      "book": "Zohar",
      "parsha": "Vayechi",
      "chapter": 16,
      "text_en": "R. Hiya discoursed on the text: . (Is. 60, 21). ‘Israel’, he said, ‘have been favoured above all the Gentiles in being entitled by God righteous, that they may obtain an everlasting inheritance in the world to come, as it is written: “Then thou shalt delight in the Lord” (Is. 58, 14). Wherefore so? Because they attach themselves to the Body of the King, as it says: “Ye that cleave unto the Lord your God are alive every one of you this day” (Deut. 4, 4).’ R. Isaac said: ‘This text of R. Hiya contains a deep allusion for “the reapers in the field”. For R. Simeon has laid down in the esoteric Agadah that the exalted inheritance of that other land is acquired by none save him who is called “righteous.” For the Matron cleaves to the Righteous One and finds delight in him, and the Righteous One assuredly inherits the Matron. So God in His love for Israel called them righteous and they are therefore meet to inherit the Matron. The reason is that they are circumcised, according to the dictum: “Whoever is circumcised and enters into the covenant and observes it becomes attached to the Body of the King, and enters into the Righteous One”, and they are therefore called righteous, and so “they shall for ever inherit the land”, to wit, the “land of the living”. They are further called in the text “the branch of my planting”, to wit, one of those shoots which God planted when He created the world, referred to in the verse,, “And the Lord God planted a garden in Eden” (Gen. 2, 8). According to another explanation, the words “And thy people are all righteous” refer to Jacob and his sons, who went down to Egypt among a stiff-necked people and all remained righteous, wherefore “they shall for ever inherit the land”, since from there they went up to inherit the holy land. AND JACOB LIVED IN THE LAND OF EGYPT. It is to be noted that this section is “closed”, i.e. no space is left in the scroll of the Law between the beginning of this section () and the end of the previous section (). Why is this? R. Jacob said: ‘It is to indicate that when Jacob died the eyes of Israel became, as it were, closed, because then they really entered on the and the Egyptians enslaved them.’ R. Simeon said: ‘It is to show that the words “and Jacob lived” are to be taken in close conjunction with the preceding sentence: “And Israel dwelt in the land of Egypt in the land of Goshen and they gat them possessions therein, and were fruitful, and multiplied exceedingly.” That is to say, just as they lived in luxury and were short of nothing, so Jacob similarly had every comfort and was short of nothing. Hence it is said of him now that “he lived”. For up to this time he had known nothing but trouble, but now he saw one of his sons in royal estate and the others virtuous and righteous, all living in the lap of luxury while he himself abode among them like good wine resting on its lees; so that now in reality he lived. SEVENTEEN YEARS. Why seventeen? R. Simeon said: ‘Jacob’s life was always one of hardship, but whenever he looked at Joseph he thought he saw his mother again, because Joseph closely resembled Rachel, and at such a time he forgot all his sorrows. When, however, Joseph was parted from him, this was a worse blow than all the previous ones, and he wept every day for the seventeen years that Joseph had been with him. Hence Providence compensated him with another seventeen years of Joseph’s company, during which he lived in ease and luxury. Tradition tells us that all those seventeen years the Divine Presence rested upon him, and therefore they were called “life”. So it says that when his sons told him that Joseph was alive, “the spirit of Jacob their father revived” (Gen. 45, 27), for up to then the spirit had been dead within him and he had not been in a state to receive another in its place, since the spirit from above does not rest on an empty spot.’ R. Jose said: ‘The Shekinah does not rest on a place which is defective or disturbed, but only in a place properly prepared, a place of joyfulness. Hence all the years that Joseph was away and Jacob was in sadness, the Shekinah did not rest on him.’ So we have learnt that R. Eleazar said in the name of R. Abba: ‘It is written, “Serve the Lord with gladness, come before his presence with singing”, to show that the service of God should be performed with joy.’ This accords with what R. Eleazar has elsewhere said, that when Elisha desired the spirit to rest upon him, he said “and now bring me a minstrel” (II Kings 3, 15). R. Abba said: ‘It has been laid down in a certain passage that the whole is derived from four sides, and that all the roots of the higher and lower beings are attached to them; and it has been further said that as one goes in another goes out, and as one is revealed another is concealed, and each one is linked to the next, and they are the origins of all.’ R. Simeon said: ‘There are three origins like the three patriarchs, and from them all the rest spread and extol the name to be crowned.’",
      "text_he": "וַיְחִי יַעֲקֹב וְגו', רִבִּי חִיָּיא פָּתַח וְאָמַר, (ישעיהו ס׳:כ״א) וְעַמֵּךְ כֻּלָּם צַדִּיקִים לְעוֹלָם יִירְשׁוּ אָרֶץ וְגו', זַכָּאִין אִינוּן יִשְׂרָאֵל, יַתִּיר מִכָּל עַמִּין עוֹבְדֵי עֲבוֹדַת כּוֹכָבִים וּמַזָּלוֹת, דְּקוּדְשָׁא בְּרִיךְ הוּא קָרָא לוֹן צַדִּיקִים. לְאַחְסִין לוֹן יְרוּתַת עַלְמִין בְּעַלְמָא דְאָתֵי, לְאִתְעֲנָגָא בְּהַהוּא עַלְמָא, כְּמָה דִכְתִיב, (ישעיהו נ״ח:י״ד) אָז תִּתְעַנֵּג עַל ה'. מַאי טַעְמָא. בְּגִין דְּמִתְדַּבְּקִין בְּגוּפָא דְמַלְכָּא, דִּכְתִיב, (דברים ד׳:ד׳) וְאַתֶּם הַדְּבֵקִים בַּה' אֱלהֵיכֶם חַיִּים כֻּלְּכֶם הַיּוֹם. רִבִּי יִצְחָק פָּתַח וְאָמַר, וְעַמֵּךְ כֻּלָּם צַדִּיקִים לְעוֹלָם יִירְשׁוּ אָרֶץ, הַאי קְרָא רָזָא עִלָּאָה אִיהוּ בֵּין מְחַצְדֵי חַקְלָא, דְּהָא בְּרָזָא דְּאַגַּדְתָּא תָּנֵי רִבִּי שִׁמְעוֹן. דְּאַחְסָנַת יְרוּתָא עִלָּאָה דְּהַהִיא אֶרֶץ, לֵית מַאן דְּיָרִית לָהּ, בַּר הַהוּא דְאִקְרֵי צַדִּיק. (ס\"א דהאי ארץ, ולית מאן דירית לה, בר ההוא דאקרי צדיק, דהא צדיק ירית למטרוניתא ודאי) דְּהָא מַטְרוֹנִיתָא בֵּיהּ אִתְדַּבְּקַת לְאִתְבַּסְּמָא, וְצַדִּיק יָרִית לְמַטְרוֹנִיתָא וַדַּאי. אוּף הָכָא, בַּחֲבִיבוּתָא דְּקוּדְשָׁא בְּרִיךְ הוּא לְיִשְׂרָאֵל, אָמַר, וְעַמֵּךְ כֻּלָּם צַדִּיקִים, וּבְגִין כָּךְ לְעוֹלָם יִירְשׁוּ אֶרֶץ, אִתְחֲזוּן לְיָרִית לְמַטְרוֹנִיתָא. מַאי טַעְמָא אִקְרוּן צַדִּיקִים, וּמַאי טַעְמָא יָרְתִין לְמַטְרוֹנִיתָא. בְּגִין דְּאִתְגַּזָּרוּ. כְּמָה דְתָנִינָן, כָּל מַאן דְּאִתְגְּזַר, וְעֲיִּיל בְּהַאי (ס\"א ברית קדישא ועייל בהאי) אַחְסָנָא, וְנָטִיר לְהַאי בְּרִית, עָאל וְאִתְדָּבַּק בְּגוּפָא דְמַלְכָּא, וְעָאל בְּהַאי צַדִּיק. וּבְגִינֵי כָּךְ אִקְרוּן צַדִּיקִים, וְעַל דָּא לְעוֹלָם יִירְשׁוּ אָרֶץ. מַאי אָרֶץ, דָּא אֶרֶץ הַחַיִּים. אַהֲדַר וְאָמַר, נֵצֶר מַטָּעַי מַעֲשֵׂה יָדַי לְהִתְפָּאֵר. נִצֶר מַטָּעַי, עֲנָפָא מֵאִינוּן עֲנָפִין, דְּנָטַע קוּדְשָׁא בְּרִיךְ הוּא כַּד בָּרָא עַלְמָא. דִּכְתִיב, (בראשית ב׳:ח׳) וַיִּטַּע ה' אֱלהִים גַּן בְּעֵדֶן מִקֶּדֶם, וְהַאי אֶרֶץ חַד מִנַּיְיהוּ. בְּגִינִי כָּךְ, נִצֶר מַטָּעַי מַעֲשֵׂה יָדַי לְהִתְפָּאֵר. דָּבָר אַחֵר, וְעַמֵּךְ כֻּלָּם צַדִּיקִים, דָּא יַעֲקֹב וּבְנוֹי דְּנָחֲתוּ לְמִצְרַיִם בֵּין עַם קְשֵׁי קְדַל, וְאִשְׁתַּכָּחוּ כֻּלְּהוּ זַכָּאִין. וּבְגִין כָּךְ כְּתִיב, לְעוֹלָם יִירְשׁוּ אֶרֶץ דְּמִּתַּמָּן סְלִיקוּ לִירַית אַרְעָא קַדִּישָׁא. וַיְחִי יַעֲקֹב בְּאֶרֶץ מִצְרַיִם, אַמַּאי פַּרְשָׁתָא דָא סְתִימָא. רִבִּי יַעֲקֹב אָמַר, בְּשַׁעְתָּא דְּמִית יַעֲקֹב, אִסְתִּימוּ עֵינֵיהוֹן דְּיִשְׂרָאֵל. רִבִּי יְהוּדָה אָמַר, דִּכְדֵין נָחֲתוּ לְגָלוּתָא, וְאִשְׁתַּעְבִּידוּ בְּהוֹן. רִבִּי שִׁמְעוֹן אָמַר, מַה כְּתִיב לְעֵילָא, וַיֵּשֶׁב יִשְׂרָאֵל בְּאֶרֶץ מִצְרַיִם בְּאֶרֶץ גּשֶׁן וַיֵּאָחֲזוּ בָהּ וַיִּפְרוּ וַיִּרְבּוּ מְאֹד. וּכְתִיב וַיְחִי יַעֲקֹב, דְּלָא אִתְחֲזֵי לְאַפְרָשָׁא בֵּין דָּא לְדָא. מָה אִינוּן קָיְימֵי בְּתַפְנוּקִין דְּמַלְכִין, וְקַבִּילוּ עִנּוּגָא וְכִסּוּפִין לְגַרְמַיְיהוּ. אוּף יַעֲקֹב נָמֵי, קַיַּים בְּתַפְנוּקֵי מַלְכִין, בְּעִנּוּגָא וְכִסּוּפָא לְגַרְמֵיהּ, לָא אִתְפְּרַשׁ דָּא מִן דָּא. וְהָכָא אִקְרֵי וַיְחִי. דְּהָא כָּל יוֹמוֹי לָא אִקְרֵי וַיְחִי, בְּגִין דְּכָל יוֹמוֹי בְּצַעֲרָא הֲווּ, בְּצַעֲרָא אִשְׁתַּכְּחָן, עֲלֵיהּ כְּתִיב, (איוב ג׳:כ״ו) לֹא שָׁלַוְתִּי וְלֹא שָׁקַטְתִּי וְלא נָחְתִּי וַיָּבֹא רֹגֶז. בָּתַר דְּנָחַת לְמִצְרַיִם, אִקְרֵי וַיְחִי. חָמָא לִבְרֵיהּ מַלְכָּא, חָמָא לְכָל בְּנוֹי זַכָּאִין צַדִּיקִין, וְכֻלְּהוּ בְּתַעֲנוּגֵי וְתַפְנוּקֵי עַלְמָא, וְהוּא יָתִיב בֵּינִיהוֹן כַּחֲמַר טַב דְּיָתִיב עַל דּוּרְדַּיֵּיהּ, כְּדֵין אִקְרֵי וַיְחִי יַעֲקֹב. וְלָא פָּרִישׁ בֵּין וַיִּפְרוּ וַיִּרְבּוּ מְאֹד לְוַיְחִי יַעֲקֹב, וְהָכִי אִתְחֲזֵי. שְׁבַע עֶשְׂרֵה שָׁנָה, מַאי טַעְמָא שְׁבַע עֶשְׂרֵה שָׁנָה. אֶלָּא אָמַר רַבִּי שִׁמְעוֹן, כָּל יוֹמוֹי דְּיַעֲקֹב בְּצַעֲרָא הֲווּ, בְּצַעֲרָא אַעֲבַר לוֹן בְּקַדְמִיתָא, כֵּיוָן דְּחָמָא לְיוֹסֵף, וְהֲוָה קָאִים קַמֵּיהּ, כַּד יַעֲקֹב מִסְתַּכֵּל בְּיוֹסֵף, הֲוָה אִשְׁתְּלִים בְּנַפְשֵׁיהּ, כְּאִילּוּ חָמָא לְאִמֵּיהּ דְּיוֹסֵף. דְּשַׁפִּירוּ דְּיוֹסֵף דָּמֵי לְשַׁפִּירוּ דְּרָחֵל. וְהֲוָה דָּמֵי בְּגַרְמֵיהּ כְּמָה דְּלָא אַעֲבַר עֲלֵיהּ צַעֲרָא בְּיוֹמוֹי. וְכַד יוֹסֵף אִתְפְּרַשׁ מִנֵּיהּ, כְּדֵין אִתְקְיַּים, לֹא שָׁלַוְתִּי וְלֹא שָׁקַטְתִּי וְלא נָחְתִּי וַיָּבֹא רֹגֶז. דְּדָא קַשְׁיָא לֵיהּ לְיַעֲקֹב מִכָּל מַה דְּעֲבַר, וּבְזִמְנָא דְּאִתְפְּרַשׁ יוֹסֵף מִנֵּיהּ, מַה כְּתִיב, (בראשית ל״ז:ב׳) יוֹסֵף בֶּן שְׁבַע עֶשְׂרֵה שָׁנָה הָיָה רוֹעֶה וְגו'. וְכָל יוֹמִין דְּיַעֲקֹב, לָא הֲוָה לֵיהּ צַעֲרָא כְּהַאי, וְהֲוָה בָּכֵי כָּל יוֹמָא לְאִינוּן שְׁבַע עֶשְׂרֵה שָׁנָה דְיוֹסֵף. מַאי קָאֲתִיבוּ לֵיהּ, (בראשית מ״ו:ד׳) וְיוֹסֵף יָשִׁית יָדוֹ עַל עֵינֶיךָ, הָא לְךָ שְׁבַע עֶשְׂרֵה שָׁנָה אָחֳרָנִין, בְּעִנּוּגִין וְתַפְנוּקִין וַהֲנָאוֹת וְכִסּוּפִין. הֲדָא הוּא דִכְתִיב וַיְחִי יַעֲקֹב בְּאֶרֶץ מִצְרַיִם שְׁבַע עֶשְׂרֵה שָׁנָה וְגו'. תָּנָא, כָּל אִינוּן שְׁנִין, שְׁכִינְתָּא יְקָרָא דְּקוּדְשָׁא בְּרִיךְ הוּא, עִמֵּיהּ אִשְׁתַּכְּחָא, וּבְגִין כָּךְ חַיִּים אִקְרוּן. תָּא חֲזֵי, כְּתִיב וַתְּחִי רוּחַ יַעֲקֹב אֲבִיהֶם, אִתְחֲזֵי דְּהָא בְּקַדְמִיתָא מִית הֲוָה הַהוּא רוּחָא דִילֵיהּ, וְלָא הֲוָה מִתְכַּוֵּין לְקַבְּלָא רוּחָא אָחֳרָא. דְּהָא רוּחָא דִלְעֵילָא, לָא שַׁרְיָא בְּרֵיקַנְיָא. אָמַר רִבִּי יוֹסֵי, שְׁכִינְתָּא לָא שַׁרְיָא, אֶלָּא בְּאֲתַר שְׁלִים, וְלָא בְּאֲתַר חָסֵר, וְלָא בְּאֲתַר פָּגִים, וְלָא בְּאֲתַר עָצִיב, אֶלָּא בְּאֲתַר דְּאִתְכַּוֵּון, בְּאֲתַר חֲדוּ. וּבְגִין כָּךְ, כָּל אִינוּן שְׁנִין דְּיוֹסֵף אִתְפְּרַשׁ מֵאֲבוֹי, וְיַעֲקֹב הֲוָה עָצִיב, לָא שַׁרְיָא בֵּיהּ שְׁכִינְתָּא. תָּנָא, אָמַר רִבִּי אֶלְעָזָר אָמַר רִבִּי אַבָּא, כְּתִיב, (תהילים ק׳:ב׳) עִבְדוּ אֶת ה' בְּשִׂמְחָה בֹּאוּ לְפָנָיו בִּרְנָנָה. לְאֲפָקָא, דְּלֵית פּוּלְחָנָא דְקוּדְשָׁא בְּרִיךְ הוּא, אֶלָּא מִגּוֹ חֶדְוָה. דְּאָמַר רִבִּי אֶלְעָזָר, לֵית שְׁכִינְתָּא שַׁרְיָא מִגּוֹ עַצְבוּת, דִּכְתִיב (מלכים ב ג׳:ט״ו) וְעַתָּה קְחוּ לִי מְנַגֵּן וְהָיָה כְּנַגֵּן הַמְנַגֵּן. מְנַגֵּן מְנַגֵּן תְּלַת זִימְנֵי אַמַּאי. בְּגִין לְאַתְעָרָא רוּחָא מִשְׁלֵימוּתָא דְּכֹלָּא, דְּהוּא רוּחַ שְׁלֵימָא. אָמַר רִבִּי אַבָּא, תַּמָּן תָּנִינָן, מֵאַרְבַּע סִטְרִין כֹּלָּא אִשְׁתַּכַּח, וְכָל שָׁרָשִׁין דְּעִלָּאִין וְתַתָּאִין בְּהוּ אֲחִידָן. וְתָנָא דָּא עָיִיל וְדָא נָפִיק דָּא סָתִים וְדָא פָּרִישׁ, אִתְאֲחַד חַד בַּחֲבֶרְתָּהּ, וְאִינוּן אֲבָהָן דְּכֹלָּא. רִבִּי שִׁמְעוֹן אָמַר, (דברים י׳:ט״ו) רַק בַּאֲבוֹתֶיךָ חָשַׁק ה', כְּתִיב בַּאֲבוֹתֶיךָ, מַמָּשׁ תְּלָתָא, וּמַשְׁמַע דִּכְתִיב רַק, רַק מַמָּשׁ, וּמֵאִלֵּין מִתְפָּרְשָׁן וּמִתְאַחֲדָן כָּל שְׁאָר אָחֳרָנִין, וְסָלְקִין שְׁמָא לְאִתְעַטְּרָא."
    },
    {
      "id": "Zohar_Vayechi.17.1",
      "book": "Zohar",
      "parsha": "Vayechi",
      "chapter": 17,
      "text_en": "R. Jose said: ‘From the day that R. Simeon left the cave, nothing was concealed from the Companions, and things became clear to them as if they had been revealed that day on Mount Sinai. But after he died, then “the fountains of the deep and the windows of heaven were closed”, and the Companions could no longer get to the bottom of things, as shown by the following instance.’ One day R. Judah was sitting at the gate of Tiberias, and he saw two camels laden with bundles of clothes. One of the bundles fell down and a flock of birds flew to the spot. Before they could reach it, however, they dispersed. Then a number of other birds came up, and perched on the rock. The men threw stones and shouted at them but they would not go away. He heard a voice saying: “The crown of crowns is plunged in darkness and does not rest on the head of the Master.” While he was still sitting, a man passed by and said: “You are not following the example of Abram, who, when the birds of prey came down upon the carcasses drove them away (Gen. 15, 11).” “I am doing so,” said R. Judah, “but they will not go”. The man turned his head away and said: “This man has not yet plucked the hairs from the head of his Master, nor shorn the Matron.” R. Judah followed him three miles asking him to explain, but he would not, so that R. Judah was greatly perturbed. One day he fell asleep under a tree and dreamt that he saw four wings outstretched and R. Simeon ascending on them with a scroll of the Law, and also with all manner of books containing hidden expositions and Agadahs. They all ascended to heaven and were lost to his view. When he woke he said: ‘Verily, since the death of R. Simeon wisdom has departed from the earth. Alas for the generation that has lost this precious jewel which used to illumine it and on which higher and lower beings were supported.’ He came and told R. Abba, who clapped his hands on his head, saying: ‘R. Simeon was the mill in which every day the goodly manna was ground. Now the mill and the manna have departed, and nothing is left of it in the world save as it were “one omerful put in a pot to be kept” (Ex. 16, 33), that is, kept in a private place and not exposed. Who now can reveal mysteries or even know them?’ R. Abba whispered to him: ‘The man that you saw was assuredly Elijah, and he was not willing to reveal secrets in order that you may appreciate the worth of R. Simeon, and that his generation may weep for him.’ He said to him: ‘He indeed deserves to be wept. Woe is me that I did not depart this life with those three who died in the sacred chamber of R. Simeon, so as not to behold this generation that has been laid low.’ He then said to him: ‘Master, tell me. It is written: “And they shall take the gold and the blue and the purple and the scarlet and the fine linen” (Ex. 28, 5). Why is there no mention here of silver, seeing that silver was also brought for an offering (v. Ex. 25, 3)?’ He replied: ‘You might ask the same question with regard to copper, which also is mentioned in one place and not in the other. As the Sacred Lamp has revealed the answer, I also may reveal it.’",
      "text_he": "תָּנָא, אָמַר רִבִּי יוֹסֵי, מִן יוֹמָא דְּאִסְתַּלִּיק רִבִּי שִׁמְעוֹן מִן מְעַרְתָּא, מִלִּין (אלין) לָא אִתְכַּסְיָין מִן חַבְרַיָא, וְרָזִין עִלָּאִין הֲווּ מִסְתַּכְּלָן וְאִתְגַּלְּיָין מִבֵּינַיְיהוּ, כְּאִלּוּ אִתְיְיהִיבוּ הַהִיא שַׁעְתָּא בְּטוּרָא דְסִינַי. בָּתַר דְּשָׁכִיב כְּתִיב, (בראשית ח׳:ב׳) וַיִּסָּכְרוּ מַעְיְינוֹת תְּהוֹם וַאֲרוּבּוֹת הַשָּׁמַיִם, וְהֲווּ חַבְרַיָיא מְרַחֲשָׁן מִלֵּי, וְלָא מִתְקַיְימֵי בְּהוּ. דְּיוֹמָא חַד הֲוָה יָתִיב רִבִּי יְהוּדָה, אֲפִתְחָא דִטְבֶרְיָה, וְחָמָא תְּרֵי גְּמַלֵּי, דְּסָלְקֵי קַטְפִירָא מֵעֲלוֹי דְּכִתְפִין, נָפַל מָטוּלָא דְּקַטְפִירָא, וְאֲתוּ צִפֳּרֵי. וְעַד לָא מָטוּ עֲלַיְיהוּ, אִתְבַּקָּעוּ. לְבָתַר אָתוּ כַּמָּה צִפֳּרִין, וְהֲווּ אָזְלֵי עֲלַיְיהוּ, וְשָׁרוּ (נ\"א ושדיאו) לוֹן בְּטַרְטִישָׁא, וְלָא מִתְבַּקְּעִין. וְהֲווּ צָוְוחִין לוֹן, וְלָא הֲווּ מִתְפָּרְשָׁן. שָׁמְעוּ חַד קָלָא, עִטְרָא דְעִטְרִין בְּקִדְרִין שַׁרְיָא, וּמָרִיהּ לְבַר. עַד דְּהֲוָה יָתִיב, עָבַר חַד גַּבְרָא, אַשְׁגַּח בְּהוּ. אָמַר, לָא קִיֵּים דָּא, הָא דִכְתִיב, (בראשית ט״ו:י״א) וַיֵּרֶד הָעַיִּט עַל הַפְּגָרִים וַיַּשֵּׁב אוֹתָם אַבְרָם. אָמַר רִבִּי יְהוּדָה, וְהָא עֲבִידְנָא וְלָא אִתְפָּרְשָׁן. אַהֲדַר רֵישֵׁיהּ הַהוּא גַבְרָא וְאָמַר, עַד לָא מָרִיט דָּא רֵישֵׁיהּ דְּמָרֵיהּ, וְעַד לָא גָּלִישׁ לְמַטְרוֹנִיתָא. רָהַט אֲבַתְרֵיהּ תְּלַת מִלִּין, וְלָא אָמַר לֵיהּ. חָלַשׁ דַּעְתֵּיהּ דְּרִבִּי יְהוּדָה. יוֹמָא חַד, אִדְמוּךְ תְּחוֹת אִילָנָא, וְחָמָא בְּחֶלְמֵיהּ, ד' גַּדְפִין מִתְתַּקְנָן, וְסָלִיק רִבִּי שִׁמְעוֹן עֲלַיְיהוּ, וְסֵפֶר תּוֹרָה עִמֵּיהּ. וְלָא שָׁבִיק כָּל סִפְרֵי רָזִין עִלָּאִין וַאֲגַדְתָּא, דְּלָא סָלִיק לוֹן בַּהֲדֵיהּ. וְסָלִיק לְהוֹן (ס\"א וסליקן ליה) לִרְקִיעָא, וְחָמָא דְמִתְכַּסְיָא מֵעֵינָא, וְלָא אִתְגַּלְיָא. כַּד אִתְעַר, אָמַר, וַדַּאי מִדְּשָׁכִיב רִבִּי שִׁמְעוֹן, חָכְמְתָא אִסְתַּלְּקַת מֵאַרְעָא. וַוי לְדָרָא דְּהַאי אַבְנָא טָבָא, דְהֲווּ מִתְחֲזָן (ס\"א דמתאחדן) מִנֵּיהּ, וְסָמְכִין עֲלֵיהּ עִלָּאִין וְתַתָּאִין, אִתְאֲבִיד מִנַּיְיהוּ. אֲתָא לְגַבֵּיהּ דְּרִבִּי אַבָּא, סָח לֵיהּ. סָלִיק רִבִּי אַבָּא יְדוֹי עַל רֵישֵׁיהּ, וּבָכָה וְאָמַר, רִבִּי שִׁמְעוֹן רֵיחַיָיא דְּטַחֲנִין מִנֵּיהּ מַנָּא טָבָא כָּל יוֹמָא, וְלָקְטִין לֵיהּ. כְּמָה דִכְתִיב, (במדבר י״א:ל״ב) הַמַּמְעִיט אָסַף עֲשָׂרָה חֳמָרִים, וְהַשְׁתָּא רֵיחַיָּיא וּמַנָּא אִסְתַּלְּקוּ וְלָא אִשְׁתָּאַר בְּעַלְמָא מִינֵיהּ, בַּר כְּמָה דִכְתִיב, (שמות ט״ז:ל״ג) קַח צִנְצֶנֶת אַחַת וְתֶן שָׁמָּה מְלֹא הָעוֹמֶר מָן וְהַנַּח אוֹתוֹ לִפְנֵי ה' לְמִשְׁמֶרֶת. וְאִלּוּ בְּאִתְגַּלְּיָיא לָא כְּתִיב, אֶלָּא לְמִשְׁמֶרֶת, לְאַצְנָעוּתָא. הַשְׁתָּא מַאן יָכִיל לְגַלָּאָה רָזִין, וּמַאן יִנְדַע לוֹן. לָחִישׁ לֵיהּ לְרִבִּי יְהוּדָה בִּלְחִישׁוּ, (אמר ליה רבי אבא) וַדַּאי הַהוּא גַבְרָא דְּחָמִית, אֵלִיָּהוּ הֲוָה. וְלָא בָּעָא לְגַלָּאָה רָזִין, בְּגִין דְּתִנְדַע שְׁבָחָא דְּרִבִּי שִׁמְעוֹן, דְּהֲוָה בְּיוֹמוֹי, וְיִבְכּוֹן דָּרָא עֲלוֹי. אָמַר לֵיהּ, דַּי לְמִבְכֵּי בְּכִיָּה עֲלֵיהּ. רִבִּי יְהוּדָה הֲוָה בָּכֵי כָּל יוֹמָא עֲלוֹי, דְּהָא אַעֲרַא עִמֵּיהּ בְּאִדְרָא קַדִּישָׁא דְּרִבִּי שִׁמְעוֹן, וּשְׁאָר חַבְרַיָיא. אָמַר לֵיהּ, וַוי דְּלָא אִסְתַּלַּקְנָא הַהוּא יוֹמָא עִם אִינוּן תְּלָתָא דְּאִסְתַּלָּקוּ, וְלָא לֶחֱמֵי דָרָא דָא, דְּהָא אִתְהַפַּךְ. אָמַר לֵיהּ, רִבִּי אֵימָא לִי, כְּתִיב, (שמות כ״ט:מ״ד) וְהֵם יִקְחוּ אֶת הַזָּהָב וְאֶת הַתְּכֵלֶת וְאֶת הָאַרְגָּמָן וְאֶת תּוֹלַעַת הַשָּׁנִי וְאֶת הַשֵּׁשׁ, וְאִילּוּ כֶּסֶף לָא כְּתִיב. וְהָא כְּתִיב זָהָב וָכֶסֶף. אָמַר לֵיהּ וְהָא נָמֵי נְחשֶׁת, דְּכֶסֶף וּנְחשֶׁת בְּחֻשְׁבְּנָא הֲווּ, וְהָכָא לָא. אֶלָּא, אִי לָא דְּגַלֵּי בּוֹצִינָא קַדִּישָׁא בְּאַתְרֵיהּ, לָא אִצְטָרִיכְנָא לְגַלָּאָה."
    },
    {
      "id": "Zohar_Vayechi.18.1",
      "book": "Zohar",
      "parsha": "Vayechi",
      "chapter": 18,
      "text_en": "He then discoursed as follows. ‘It is written: “Mine is the silver and mine is the gold, saith the Lord” (Haggai 2, 8). On many occasions we have pondered over the question, what holiness is there in these priestly garments? We have, however, been taught that there is holiness in every place, and that these garments are after the supernal pattern, as we have learnt: “There is a High Priest above and a high priest below, raiment of honour above and raiment of honour below.” As for the omission of silver and copper, these were assigned to another place, as it is written, “All the pillars of the court round about shall be filleted with silver”, and again, “and their sockets of brass” (Ex. 27, 17). These were the instruments for the service of the Tabernacle; but this raiment of honour was only to be used by the High Priest and by no other.’",
      "text_he": "פָּתַח וְאָמַר, (חגי ב׳:ח׳) לִי הַכֶּסֶף וְלִי הַזָּהָב נְאֻם ה', הַיְינוּ דִכְתִיב, (תהילים קט״ו:ט״ז) הַשָּׁמַיִם שָׁמַיִם לַה'. בְּכַמָּה אֲתַר אִסְתַּכַּלְנָא בְּאִלֵּין מָאנֵי דְּקוּדְשָׁא, דִּכְתִיב, (ויקרא טו) בִּגְדֵי קֹדֶשׁ הֵם, וּכְתִיב, (שמות כ״ח:ד׳) וְעָשׂוּ בִּגְדֵי קֹדֶשׁ. מַאי קְדוּשָּׁה הָכָא. אֶלָּא הָכִי תָּנִינָן, קְדוּשָּׁה אִינוּן בְּכָל אֲתַר. וּכְתִיב בִּגְדֵי קֹדֶשׁ הֵם. וְעָשִׂיתָ בִּגְדֵי קֹדֶשׁ, כְּגַוְונָא דִלְעֵילָא. דְּתַנְיָא כֹּהֵן גָּדוֹל לְעֵילָא, כֹּהֵן גָּדוֹל לְתַתָּא, לְבוּשִׁין דִּיקָר לְעֵילָא, לְבוּשִׁין דִּיקָר לְתַתָּא. וּמַה דְּלָא אָמַר כֶּסֶף וּנְחשֶׁת, לְאֲתַר אָחֳרָא אִסְתַּלִּיקוּ. דִּכְתִיב (שמות כ״ז:י״ח) כָּל עַמּוּדֵי הֶחָצֵר סָבִיב מְחוּשָׁקִים כָּסֶף וְגו', וּכְתִיב וְאַדְנֵיהֶם נְחשֶׁת. דְּאִינוּן מָאנֵי שִׁמּוּשָׁא, לְאִשְׁתַּמָּשָׁא מַשְׁכְּנָא בְּהוּ. אֲבָל הָכָא בְּאִלֵּין לְבוּשִׁין דִּיקָר, לָא בָּעֵי לְאִשְׁתַּמָּשָׁא בְּהוּ בַּר נָשׁ אָחֳרָא, בַּר מִכַּהֲנָא רַבָּא, דִּרְבוּ מְשַׁח קוּדְשָׁא עַל רֵישֵׁיהּ. דִּכְתִיב (שמות כ״ח:ב׳) וְעָשִׂיתָ בִּגְדֵי קֹדֶשׁ לְאַהֲרֹן אָחִיךָ לְכָבוֹד וּלְתִפְאָרֶת. דִּבְאִינוּן לְבוּשִׁין דָּמֵי לְגַוְונָא דִלְעֵילָא."
    },
    {
      "id": "Zohar_Vayechi.19.1",
      "book": "Zohar",
      "parsha": "Vayechi",
      "chapter": 19,
      "text_en": "AND THE TIME DREW NEAR THAT ISRAEL MUST DIE. R. Judah said: ‘Alas, for the ignorance of mankind! They see not, neither do they hear, nor know that every day the voice of a herald goes forth and resounds through two hundred and fifty worlds. We have learnt that when the herald goes forth one of these worlds shakes and trembles, and there issue from it two birds whose abode is beneath the tree wherein is the appearance of life and death, one towards the South and the other towards the North, one when the day dawns and one when it departs. Both proclaim what they hear from the herald. They then desire to return to their own place aloft, but their feet slip in the hollow of the great abyss and they are fastened there till midnight. Then the herald proclaims, and the sons of men are also “snared like birds caught in the trap”.’ R. Judah said: ‘The day when a man’s feet are caught and his time approaches to die is called “the day of the Lord”, because then his spirit returns to Him. We have learnt that at that time a holy Crown, to wit, the seventh, is entrusted with his spirit, or, if he comes from the side of Might () the eighth Crown; beyond that his days cannot be prolonged, as it says, “yet is their pride and labour but sorrow” (Ps. 90, 10); where there is no foundation the building cannot be firm.’ R. Judah said: ‘Happy are the righteous when God is pleased to take back their spirit to Himself. But if a man is not adjudged worthy, woe to his spirit, which has to be purified and to be prepared before it can be drawn to the Body of the King; and if it is not prepared, woe to it that it must roll about “like a stone in a sling” (cf. I Sam.). Further, we have learnt: “If the soul is worthy, great is the bliss reserved for it in the other world, as it is written, “No eye hath seen save thine, O Lord, what thou wilt do for him that trusts in thee” (Is. 64, 3).’ R. Jose said: ‘When a man’s appointed time draws near, proclamation is made concerning him for thirty days, and even the birds of the heaven announce his doom; and if he is virtuous, his coming is announced for thirty days among the righteous in the Garden of Eden. We have learnt that during those thirty days his soul departs from him every night and ascends to the other world and sees its place there, and during those thirty days the man has not the same consciousness or control of his soul as previously.’ R. Judah said: ‘From the first arrival of those thirty days a man’s shadow becomes faint and his form is not outlined clearly on the ground.’",
      "text_he": "תַּנְיָא. וַיִּקְרְבוּ יְמֵי יִשְׂרָאֵל לָמוּת. אָמַר רִבִּי יְהוּדָה, וַוי לְעַלְמָא, דְּהָא בְּנֵי נָשָׁא לָא חָמָאן וְלָא שְׁמָעָן, וְלָא יָדְעִין דְּהָא כָּל יוֹמָא וְיוֹמָא, קָלָא דְּכָרוֹזָא אִשְׁתְּמַע, בְּמָאתָן וְחַמְשִׁין עָלְמִין. תָּנָא עַלְמָא חָדָא, אִשְׁתְּמוֹדַע לְעֵילָא. וְכַד כָּרוֹזָא נָפִיק, הַהוּא עַלְמָא מִזְדַּעְזְעָא וּמִתְחַלְחְלָא. נָפְקֵי (קסב ע\"ב) תְּרֵין צִפֳּרִין, דְּאִסְתַּלָּקוּ מֵהַהוּא עַלְמָא, דִּמְדוֹרֵיהוֹן תְּחוֹת אִילָנָא דְּחֵיזוּ דְחַיֵּי וּמוֹתָא בֵּיהּ. נָפְקָא חַד צִפּוֹרָא לִסְטַר דָּרוֹמָא וְחַד צִפּוֹרָא לִסְטַר צָפוֹנָא, וְחַד צִפּוֹרָא כַּד נָהִיר יְמָמָא, וְחַד כַּד אִתְחֲשַׁךְ יְמָמָא. כָּל חַד וְחַד קָרֵי וּמַכְרְזָא, מַה דְּשָׁמְעִין מֵהַהוּא כָּרוֹזָא. לְבָתַר בָּעוּ לְאִסְתַּלָּקָא לְאַתְרַיְיהוּ, וּמִשְׁתַּמְטֵי רַגְלַיְיהוּ בְּנוּקְבָא דִתְהוֹמָא רַבָּא, וּמִתְלַכְּדָן בְּגַוֵּיהּ, עַד דְּאִתְפְּלִיג לֵילְיָא. כַּד אִתְפְּלִיג לֵילְיָא, כָּרוֹזָא קָרֵי, (קהלת ט׳:י״ב) וְכַצִּפֳּרִים הָאֲחֻזוֹת בַּפָּח כָּהֵם יוּקָשִׁים בְּנֵי הָאָדָם. אָמַר רִבִּי יְהוּדָה, בְּשַׁעְתָּא דְּמִתְלַכְּדָן רַגְלוֹי דִּבְנֵי נָשָׁא, וְיוֹמוֹי אִתְקְרִיבוּ, הַהוּא יוֹמָא, אִתְקְרֵי יוֹם ה', לְאֲתָבָא רוּחֵיהּ לֵיהּ. תָּנָא בְּהַהִיא שַׁעְתָּא, פַּקְדָא הַהוּא כִּתְרָא קַדִּישָׁא, עַל רוּחֵיהּ. וּמַאן אִיהוּ, דִּכְתִיב, (תהילים צ׳:י׳) יְמֵי שְׁנוֹתֵינוּ בָהֶם שִׁבְעִים שָׁנָה. וְהִיא כִּתְרָא שְׁבִיעָאָה דְּכֹלָּא. וְאִם מִסִּטְרָא דִגְבוּרָה קָאֳתֵי, כְּתִיב, וְאִם בִּגְבוּרוֹת שְׁמֹנִים שָׁנָה דְּכִתְרָא דִּגְבוּרָה תְּמִינָאָה הֲוֵי, מִכָּאן וּלְהָלְאָה, לֵית אֲתַר לְאִתְמְשַׁךְ, כְּמָה דְאַתְּ אָמֵר, וְרָהְבָּם עָמָל וָאָוְן. בְּאֲתַר דְּלָא הֲוֵי יְסוֹדָא, בִּנְיָינָא לָא אִתְקְיַּים. אָמַר רִבִּי יְהוּדָה, זַכָּאִין אִינוּן צַדִּיקַיָא, כַּד קוּדְשָׁא בְּרִיךְ הוּא בָּעָא לְאֲתָבָא רוּחֵיהּ לֵיהּ, וּלְשָׁאֲבָא הַהוּא רוּחָא בְּגַוֵּיהּ. דְּתַנְיָא, בְּשַׁעְתָּא דְּקוּדְשָׁא בְּרִיךְ הוּא בָּעָא לְאֲתָבָא רוּחֵיהּ לֵיהּ, אִי זַכָּאָה הוּא הַהוּא רוּחָא, מַה כְּתִיב, (קהלת י״ב:ז׳) וְהָרוּחַ תָּשׁוּב אֶל הָאֱלהִים אֲשֶׁר נְתָנָהּ. וְאִי לָא אִשְׁתַּכַּח זַכָאָה, וַוי לְהַהוּא רוּחָא, דְּבָעֵי לְאִסְתַּחָאָה בְּנוּרָא דְּדָלִיק, וּלְאִתְתַּקָּנָא בְּגִין לְאִשְׁתָּאֲבָא בְּגוּפָא דְמַלְכָּא וְאִי לָא אִתְתַּקָּנַת, וַוי לְהַהוּא רוּחָא, דְמִתְגַּלְגְּלָא כְּאַבְנָא בְּקוֹסְפִיתָא, דִּכְתִיב, (שמואל א כ״ה:כ״ט) וְאֶת נֶפֶשׁ אֹיְבֶיךָ יְקַלְּעֶנָּה בְּתוֹךְ כַּף הַקָּלַע. תַּנְיָא, אִי הַהוּא רוּחָא זָכֵי, כַּמָּה טָבִין גְּנִיזִין לֵיהּ בְּהַהוּא עַלְמָא. דִּכְתִיב, (ישעיהו ס״ד:ג׳) עַיִן לא רָאָתָה אֱלֹהִים זוּלָתְךָ יַעֲשֶׂה לִמְחַכֵּה לוֹ. אָמַר רִבִּי יוֹסֵי, כַּד הַהוּא בַּר נָשׁ אִתְקְרִיבוּ יוֹמוֹי, תְּלָתִין יוֹמִין מַכְרִיזֵי עֲלוֹי בְּעַלְמָא וְאֲפִילּוּ צִפֳּרֵי שְׁמַיָא מַכְרִיזִין עֲלוֹי. וְאִי זַכָּאָה הוּא, תְּלָתִין יוֹמִין מַכְרִיזִין עֲלוֹי בֵּין צַדִּיקַיָא, בְּגִינְתָא דְעֵדֶן. תָּנָא, כָּל אִינוּן תְּלָתִין יוֹמִין, נִשְׁמָתֵיהּ נָפְקַת מִנֵּיהּ בְּכָל לֵילְיָא, וְסָלְקַת וְחָמַאת דּוּכְתָּהּ בְּהַהוּא עַלְמָא, וְהַהוּא בַּר נָשׁ לָא יָדַע, וְלָא אַשְׁגַּח, וְלָא שַׁלִּיט בְּנִשְׁמָתֵיהּ, כָּל אִינוּן תְּלָתִין יוֹמִין כְּמָה דְּהֲוָה בְּקַדְמִיתָא. דִּכְתִיב, (קהלת ח׳:ח׳) אֵין אָדָם שַׁלִּיט בָּרוּחַ לִכְלא אֶת הָרוּחַ וְגו'. אָמַר רִבִּי יְהוּדָה, מִכַּד שָׁרָאן אִינוּן תְּלָתִין יוֹמִין, צַלְמָא דְּבַּר נָשׁ אִתְחֲשַׁךְ, וְדִיוּקְנָא דְאִתְחֲזֵי בְּאַרְעָא אִתְמְנָעַת."
    },
    {
      "id": "Zohar_Vayechi.20.1",
      "book": "Zohar",
      "parsha": "Vayechi",
      "chapter": 20,
      "text_en": "R. Isaac one day sat himself at R. Judah’s door in great sadness. The latter coming out and finding him in this condition said to him: ‘What is the matter to-day?’ He replied: ‘I have come to ask you three things. One is that whenever you repeat any of my expositions of the Torah you should give them in my name. The second is that you should train my son Joseph in the Torah; and the third is that you should go every seven days and pray over my grave.’ Said R. Judah: ‘What makes you think you are going to die?’ He answered: ‘My soul has lately been leaving me in the night and not enlightening me with dreams as it used to do. Furthermore, when I bow down in the course of my prayers, I notice that my shadow does not appear on the wall, and I imagine the reason to be that the herald has gone forth and made proclamation regarding me.’ R. Judah replied: ‘I will carry out your requests. But I will ask you also to reserve a place for me by your side in the other world, as we were together in this.’ R. Isaac wept and said: ‘I beg of you not to leave me for the rest of my days.’ They then went to R. Simeon, whom they found studying the Torah. Raising his eyes, R. Simeon saw R. Isaac and the Angel of Death running and dancing before him, so going to the door, he took R. Isaac by the hand and said: ‘I ordain that he who is wont to enter shall enter and he who is not wont shall not enter.’ Thereupon R. Isaac and R. Judah entered and the Angel of Death was kept outside. R. Simeon looked at R. Isaac and saw that his time had not yet come, and that he had respite till the eighth hour of the day, so he made him sit down before him and study the Torah. R. Simeon then said to his son R. Eleazar: ‘Sit by the door and speak with no one, and if anyone wants to come in, swear to him that he may not.’ He then said to R. Isaac: ‘Have you seen to-day the image of your father? For so we have learnt, that at the hour of a man’s departure from the world, his father and his relatives gather round him, and he sees them and recognizes them, and likewise all with whom he associated in this world, and they accompany his soul to the place where it is to abide.’ R. Isaac replied: ‘So far I have not seen.’ R. Simeon then arose and said: ‘Sovereign of the Universe! R. Isaac is well known among us, and he is one of the seven eyes of the world here. Now that I hold him, give him to me.’ A voice then went forth and said: ‘The throne of his Master is near the wings of R. Simeon. Lo, he is thine, and he shall accompany thee when thou goest in to abide on thy throne.’ R. Eleazar now saw the Angel of Death coming up, and said to him: ‘The doom of death cannot fall in the place where R. Simeon is.’ R. Simeon then said to his son: ‘Come in here and take hold of R. Isaac, since I see that he is afraid.’ R. Eleazar did so, and R. Simeon turned round and began to study. R. Isaac then fell asleep and saw his father in a dream. He said to him: ‘My son, happy is thy portion both in this world and in the world to come. For among the leaves of the tree of life in the Garden of Eden there is placed a great tree, mighty in both worlds, which is R. Simeon, son of Yohai, and he shelters thee with his boughs.’ Said R. Isaac to him: ‘Father, what is my portion there?’ He replied: ‘Three days ago they roofed in thy chamber and prepared for thee, placing windows on all four sides to let light in upon thee, so that when I saw thy place I rejoiced, and said: Happy is thy portion; save that thy son has not yet learnt sufficient Torah.’ And behold now, twelve righteous Companions were eager to visit thee, and when we were on the point of departing a voice went forth through all worlds saying “Ye companions that stand here, be proud of R. Simeon, for he has made a request and it has been granted to him.” Nor is thisall, for there are here seventy crowned places belonging to him, and every place has doors opening to seventy worlds, and every world is open to seventy channels, and every channel is open to seventy supernal crowns, and from there paths are opened out to the Ancient and Inscrutable One, to give a view of that supernal delight which illumines and beatifies all, as it says, “to see the pleasantness of the Lord and to visit his temple”.’",
      "text_he": "רִבִּי יִצְחָק הֲוָה יָתִיב יוֹמָא חַד אֲפִתְחָא דְּרִבִּי יְהוּדָה, וְהֲוָה עָצִיב. נָפִיק רִבִּי יְהוּדָה, אַשְׁכְּחֵיהּ לְתַרְעֵיהּ, דְּהֲוָה יָתִיב וְעָצִיב. אָמַר לֵיהּ (צ\"ל מה) מַאן יוֹמָא דֵין מִשְּׁאָר יוֹמִין. אָמַר לֵיהּ, אָתֵינָא לְגַבָּךְ, לְמִבְעֵי מִינָךְ תְּלַת מִלִּין, חַד, דְּכַד תֵּימָא מִלֵּי דְאוֹרַיְיתָא, וְתַדְכַּר מֵאִינוּן מִלִּין דְּאֲנָא אֲמִינָא, דְּתֵימָא לוֹן מִשְּׁמִי, בְּגִין לְאַדְכָּרָא שְׁמִי. וְחַד דְּתִזְכֵּי לְיוֹסֵף בְּרִי בְּאוֹרַיְיתָא. וְחַד, דְּתֵיזִיל לְקִבְרִי כָּל ז' יוֹמִין, וְתִבְעֵי בָּעוּתִיךְ עָלַי. אָמַר לֵיהּ מִנַּיִן לָךְ. אָמַר לֵיהּ, הָא נִשְׁמָתִי אִסְתַּלְּקַת מִינִי בְּכָל לֵילְיָא, וְלָא אַנְהִיר לִי בְּחֶלְמָא כְּמָה דְּהֲוָה בְּקַדְמִיתָא. וְעוֹד דְּכַד אֲנָא מַצְלֵינָא וּמָטִינָא לְשׁוֹמֵעַ תְּפִלָּה, אַשְׁגַּחְנָא בְּצוּלְמִי דִילִי בְּכוֹתְלָא, וְלָא חָמִינָא לֵיהּ. וְאֲמִינָא דְּהוֹאִיל וְצַלְמָא אִתְעֲבַר וְלָא אִתְחֲזֵי, דְּהָא כָּרוֹזָא נָפִיק וְכָרִיז. דִּכְתִיב, (תהילים ל״ט:ז׳) אַךְ בְּצֶלֶם יִתְהַלֶּךְ אִישׁ, כָּל זִמְנָא דְּצוּלְמָא דְּבַר נָשׁ לָא יִתְעֲבַר מִנֵּיהּ, יִתְהַלֶּךְ אִישׁ, וְרוּחֵיהּ אִתְקַיְּימָא בְּגַוֵּיהּ. אִתְעֲבַר צוּלְמָא דְבַר נָשׁ וְלָא אִתְחֲזֵי, אִתְעֲבַר מֵהַאי עָלְמָא. אָמַר לֵיהּ, וּמֵהָכָא, דִּכְתִיב, (איוב ח׳:ט׳) כִּי צֵל יָמֵינוּ עֲלֵי אָרֶץ. אָמַר לֵיהּ, כָּל אִלֵּין מִלִּין דְּאַתְּ בָּעֵי עֲבִידְנָא. אֲבָל בָּעִינָא מִינָךְ דִּבְהַהוּא עַלְמָא, תְּבָרִיר דּוּכְתָּאי גַּבָּךְ, כְּמָה דַהֲוֵינָא בְּהַאי עַלְמָא. בָּכָה רִבִּי יִצְחָק וְאָמַר, בְּמָטוּ מִינָךְ, דְּלָא תִּתְפָּרֵשׁ מִנָּאי כָּל אִלֵּין יוֹמִין. אֲזְלוּ לְגַבֵּיהּ דְּרִבִּי שִׁמְעוֹן, אַשְׁכְּחוּהוּ דְּהֲוָה לָעֵי בְּאוֹרַיְיתָא, זָקִיף עֵינוֹי רִבִּי שִׁמְעוֹן, וְחָמָא לְרִבִּי יִצְחָק, וְחָמָא לְמַלְאַךְ הַמָּוֶת דְּרָהִיט קַמֵּיהּ, וְרָקִיד קַמֵּיהּ. קָם רִבִּי שִׁמְעוֹן, אָחִיד בִּידֵיהּ דְּרִבִּי יִצְחָק. אָמַר, גּוֹזַרְנָא, מַאן דְּרָגִיל לְמֵיעַל, יֵעוּל. וּמַאן דְּלָא רָגִיל לְמֵיעָאל, לָא יֵיעוּל. עָאלוּ רִבִּי יִצְחָק וְרִבִּי יְהוּדָה, קָטִיר מַלְאַךְ הַמָּוֶת לְבַר. אַשְׁגַּח רִבִּי שִׁמְעוֹן, וְחָמָא דְּעַד כְּעַן לָא מָטָא עִדָּנָא, דְּהָא עַד תְּמַנְיָא שַׁעְתֵּי דְיוֹמָא הֲוָה זִמְנָא. אוֹתְבֵיהּ קַמֵּי רִבִּי שִׁמְעוֹן, וְהֲוָה לָעֵי לֵיהּ בְּאוֹרַיְיתָא. אָמַר רַבִּי שִׁמְעוֹן לְרִבִּי אֶלְעָזָר בְּרִיהּ, תִּיב אֲפִתְחָא וּמַה (צ\"ל ומאן) דְּתֶחמֵי, לָא תִשְׁתָּעֵי בַּהֲדֵיהּ. וְאִי יִבְעֵי לְמֵיעָאל הָכָא, אוֹמֵי אוֹמָאָה דְּלָא לֵיעוֹל. אָמַר רִבִּי שִׁמְעוֹן לְרִבִּי יִצְחָק, חָמִית דִּיוּקְנָא דְּאֲבוּךְ יוֹמָא דָא, אוֹ לָא. דְּהָא תָּנִינָן, בְּשַׁעְתָּא דְבַר נָשׁ אִסְתַּלַּק מֵעַלְמָא, אֲבוֹי וְּקְרֵיבוֹי מִשְׁתַּכְּחִין תַּמָּן עִמֵּיהּ, וְחָמָא לוֹן וְאִשְׁתְּמוֹדַע לוֹן, וְכָל אִינוּן דְּהֲוָה מְדוֹרֵיהּ גַּבַּיְיהוּ בְּהַהוּא עַלְמָא בְּדַרְגָּא חַד, כֻּלְּהוּ מִתְכַּנְּשֵׁי וּמִשְׁתַּכְּחֵי עִמֵּיהּ, וְאָזְלִין עִם נִשְׁמָתֵיהּ, עַד אֲתַר דְּתִשְׁרֵי בְּאַתְרֵיהּ. אָמַר, עַד כְּעָן לָא חָמֵינָא. אַדְּהָכִי קָם רִבִּי שִׁמְעוֹן וְאָמַר, מָארֵי דְעַלְמָא, אִשְׁתְּמוֹדַע רִבִּי יִצְחָק לְגַבָּן, וּמֵאִנּוּן שִׁבְעָה עַיְינִין דְּהָכָא הוּא. הָא אֲחִידְנָא בֵּיהּ, וְהַב לִי. נָפַק קָלָא וְאָמַר, כּוּרְסְיָיא (ס\"א טסיסה) דְמָארֵיהּ קְרִיבָא בְּגַדְפוֹי דְּרִבִּי שִׁמְעוֹן, הָא דִידָךְ הוּא, וְעִמָּךְ תַּיְיתֵיהּ בְּזִימְנָא דְתִיעוֹל לְמִשְׁרֵי בְּכוּרְסְיָךְ. אָמַר רִבִּי שִׁמְעוֹן, וַדַּאי. אַדְּהָכִי, חָמָא רִבִּי אֶלְעָזָר דְּהֲוָה אִסְתַּלִּיק מַלְאַךְ הַמָּוֶת. וְאָמַר, לֵית קוּפְטְרָא דְּטִיפְסָא, בְּאֲתַר דְּרִבִּי שִׁמְעוֹן בֶּן יוֹחָאי שְׁכִיחַ. אָמַר רִבִּי שִׁמְעוֹן לְרִבִּי אֶלְעָזָר בְּרֵיהּ, עוּל הָכָא, וְאָחִיד בֵּיהּ בְּרִבִּי יִצְחָק, דְּהָא חָמֵינָא בֵּיהּ דְּמִסְתָּפֵי. עָאל רִבִּי אֶלְעָזָר, וְאָחִיד בֵּיהּ. וְרִבִּי שִׁמְעוֹן אַהֲדַר אַנְפֵּיהּ וְלָעֵי בְּאוֹרַיְיתָא. נַיִים רִבִּי יִצְחָק, וְחָמָא לְאֲבוֹי. אָמַר לֵיהּ, בְּרִי, זַכָּאָה חוּלָקָךְ בְּעַלְמָא דֵין וּבְעַלְמָא דְאָתֵי. דְּהָא בֵּין טַרְפֵּי אִילָנָא דְחַיֵּי דְּגִנְתָא דְעֵדֶן, אִתְיְהִיב (את יתיב) אִילָנָא רַבָּא וְתַקִּיף בִּתְרֵין עָלְמִין, רִבִּי שִׁמְעוֹן בֶּן יוֹחָאי הוּא. דְּהָא הוּא אָחִיד לָךְ בְּעַנְפוֹי, זַכָּאָה חוּלָקָךְ בְּרִי. אָמַר לֵיהּ אַבָּא, וּמָה אֲנָא הָתָם. אָמַר לֵיהּ, תְּלַת יוֹמִין הֲווּ דְּחָפוּ אִדְרָא דְּמִשְׁכָּבָךְ. וְתַקִּינוּ לָךְ כֵּיוַן פְּתִיחָן, לְאַנְהָרָא לָךְ מֵאַרְבַּע סִטְרִין דְּעַלְמָא. וְאֲנָא חָמֵינָא דּוּכְתֵּיךְ וְחָדֵינָא, דַּאֲמֵינָא זַכָּאָה חוּלָקָךְ בְּרִי. בַּר דְּעַד כְּעָן, בְּרָךְ לָא זָכֵי בְּאוֹרַיְיתָא. וְהָא הַשְׁתָּא הֲוֵי זְמִינִין לְמֵיתֵי גַּבָּךְ, תְּרֵיסַר צַדִּיקַיָא דְחַבְרַיָיא, וְעַד דַּהֲוֵינָא נָפְקֵי, אִתְעַר קָלָא בְּכֻלְּהוּ עַלְמִין, מַאן חַבְרִין (ס\"א שבילין) דְּקָיְימִין הָכָא, אִתְעֲטָרוּ, בְּגִינֵיהּ דְּרִבִּי שִׁמְעוֹן. שְׁאֶלְתָּא שָׁאִיל, וְאִתְיְיהִיב לֵיהּ. וְלָא דָא בִּלְחוֹדוֹי, דְּהָא שִׁבְעִין דּוּכְתֵּי מִתְעַטְּרָן הָכָא דִילֵיהּ. וְכָל דּוּכְתָּא וְדוּכְתָּא, פָּתְחִין פְּתִיחָן לְשִׁבְעִין עָלְמִין. וְכָל עַלְמָא וְעַלְמָא אִתְפַּתַּח לְע' רְהִיטִין. וְכָל רְהִיטָא וּרְהִיטָא, אִתְפַּתַּח לְשִׁבְעִין כִּתְרִין עִלָּאִין. וּמִתַּמָּן אִתְפַּתָּחוּ אָרְחִין לְעַתִּיקָא סְתִימָאָה דְּכֹלָּא, לְמֶחֱמֵי בְּהַהוּא נְעִימוּתָא עִלָּאָה דְּנָהֲרָא, וּמְהַנְיָא לְכֹלָּא. כְּמָה דְאַתְּ אָמֵר, (תהילים כ״ז:ד׳) לַחֲזוֹת בְּנוֹעַם ה' וּלְבַקֵּר בְּהֵיכָלוֹ. מַהוּ וּלְבַקֵּר בְּהֵיכָלוֹ. הַיְינוּ דִכְתִיב, (במדבר י״ב:ז׳) בְּכָל בֵּיתִי נְאֱמָן הוּא."
    },
    {
      "id": "Zohar_Vayechi.21.1",
      "book": "Zohar",
      "parsha": "Vayechi",
      "chapter": 21,
      "text_en": "Said R. Isaac: ‘Father, how long am I granted to be in this world?’ He answered: ‘I am not permitted to tell, nor is this made known to a man. But in the great feast of R. Simeon, thou shalt prepare his table.’ R. Isaac then awoke, his face full of smiles. R. Simeon, observing him, said: ‘You have heard something, have you not?’ ‘Assuredly,’ he replied; and he then told him his dream, and prostrated himself before him. It is related that from that day R. Isaac diligently taught his son the Torah and always had him with him. When he went in to R. Simeon, he used to leave his son outside, and when he sat before R. Simeon he applied to himself the verse: “O Lord, I am oppressed, be thou my surety” (Is. 38, 14). We have learnt that on the dread day when a man’s time comes to depart from the world, four quarters of the world indict him, and punishments rise up from all four quarters, and four elements fall to quarrelling and seek to depart each to its own side. Then a herald goes forth and makes proclamation, which is heard in two hundred and seventy worlds. If the man is worthy, all the worlds welcome him with joy, but if not, alas for that man and his portion! We have learnt that when the herald makes proclamation, a flame goes forth from the North and passes through the “stream of fire”, and divides itself to the four quarters of the world to burn the souls of sinners. It then goes forth and flies up and down till it alights between the wings of a black cock. The cock then flaps its wings and cries out at the threshold of the gate. The first time it cries: “Behold, the day cometh burning like a furnace, etc.” (Mal. 3, 19). The second time it cries: “For lo, he that formeth the mountains and createth the wind and declareth unto man what is his thought” (Amos 4, 13); that is the time when a man’s deeds testify against him and he acknowledges them. The third time is when they come to remove his soul from him and the cock cries: “Who would not fear thee, King of the nations? For to thee doth it appertain, etc.” (Jer. 10, 7). Said R. Jose: ‘Why must it be a black cock?’ R. Judah replied: ‘Whatever the Almighty does has a mystic significance. We have learnt that chastisement does not fall save upon a place which is akin to it. Now black is the symbol of the side of Judgement, and therefore when the flame goes forth, it strikes the wings of a black cock, as being the most appropriate. So when man’s judgement hour is near, it commences to call to him, and no one knows save the patient himself, as we have learnt, that when a man is ill and his time is approaching to depart from the world a new spirit enters into him from above, in virtue of which he sees things which he could not see before, and then he departs from the world. So it is written: “For man shall not see me and live”; in their lifetime they may not see, but at the hour of death they may. We have further learnt that at the time of a man’s death he is allowed to see his relatives and companions from the other world. If he is virtuous, they all rejoice before him and give him greeting. but if not, then he is recognized only by the sinners who every day are thrust down to Gehinnom. They are all in great gloom and begin and end their converse with “woe!”. Raising his eyes, he beholds them like a flame shooting up from the fire, and he also exclaims “woe!”. We have learnt that when a man’s soul departs from him, all his relatives and companions in the other world join it and show it the place of delight and the place of torture. If he is virtuous he beholds his place and ascends and sits there and enjoys the delights of the other world. But if he is not virtuous, his soul remains in this world until his body is buried in the dust, and then the executioners take hold of him and drag him down to Dumah and to his appointed storey in Gehinhom. R. Judah said: ‘For seven days the soul goes to and fro from his house to his grave, and from his grave to his house, mourning for the body, as it is written: “His flesh shall suffer pain for him, and his soul shall mourn for it” (Job 14, 22), and it grieves to behold the sadness in the house. We have learnt that after seven days the body begins to decay, and the soul goes in to its place. It enters the cave of Machpelah, where it is allowed in up to a certain point according to its deserts. It then reaches the place of the Garden of Eden and meets the Cherubim and the flashing sword which is in the lower Garden of Eden, and if it is worthy to enter, it enters. We have learnt that four pillars are waiting there with the form of a body in their hands, and with this it gleefully clothes itself and then remains in its appointed circle in the Garden of Eden for its allotted time. Then a herald makes proclamation and a pillar of three colours is brought forward, which is called “the habitation of Mount Zion” (Is. 4, 5). By means of this pillar it ascends to the gate of righteousness, in which are Zion and Jerusalem. If it is worthy to ascend further, then happy is its portion and lot that it becomes attached to the Body of the King. If it is not worthy to ascend further, then “he that is left in Zion and he that remaineth in Jerusalem shall be called holy” ( 3). But if it is privileged to ascend further, then it beholds the glory of the King, and enjoys the supernal delight from the place which is called Heaven. Happy he that is vouchsafed this grace. R. Jose said: ‘There is a superior grace and an inferior grace. The superior grace is above the heavens, as it is written: “For great the heaven is thy kindness” (Ps. 108, 5). Of the inferior grace it is written: “For great the heaven is thy kindness” ( 57, 11), and to this class belong the “faithful kindnesses of David” (Is. 55, 3).’",
      "text_he": "אָמַר לֵיהּ, אַבָּא, כַּמָּה זִמְנָא יְהִיבוּ לִי בְּהַאי עַלְמָא, אָמַר לֵיהּ, לֵית לִי רְשׁוּתָא וְלָא מוֹדָעֵי לֵיהּ לְבַר נָשׁ. אֲבָל בְּהִלּוּלָא רַבָּא דְּרִבִּי שִׁמְעוֹן, תְּהֵא מְתַקֵּן פָּתוֹרֵיהּ. כְּמָא דְאַתְּ אָמֵר, (שיר השירים ג׳:י״א) צְאֶינָה וּרְאֶינָה בְּנוֹת צִיּוֹן בַּמֶּלֶךְ שְׁלֹמֹה בָּעֲטָרָה שֶׁעִטְּרָה לוֹ אִמוֹ בְּיוֹם חֲתֻנָּתוֹ וּבְיוֹם שִׂמְחַת לִבּוֹ. אַדְּהָכִי אִתְעַר רִבִּי יִצְחָק, וְהֲוָה חָיִיךְ, וְאַנְפּוֹי נְהִירִין. חָמָא רִבִּי שִׁמְעוֹן, וְאִסְתַּכֵּל בְּאַנְפּוֹי. אָמַר לֵיהּ, מִלָּה חַדְתָּא שְׁמַעְתָּא. אָמַר לֵיהּ, וַדַּאי. סָח לֵיהּ, אִשְׁתַּטַּח קַמֵּיהּ דְּרִבִּי שִׁמְעוֹן. תָּאנָא, מֵהַהוּא יוֹמָא, הֲוָה רִבִּי יִצְחָק אָחִיד לִבְרֵיהּ בִּידֵיהּ, וְלָעֵי לֵיהּ בְּאוֹרַיְיתָא, וְלָא הֲוָה שַׁבְקֵיהּ. כַּד הֲוָה עָאל קַמֵּיהּ דְּרִבִּי שִׁמְעוֹן, אוֹתְבֵיהּ לִבְרֵיהּ לְבַר, וְיָתִיב קַמֵּיהּ דְּרִבִּי שִׁמְעוֹן, וְהֲוָה קָרֵי קַמֵּיהּ (ישעיהו ל״ח:י״ד) ה' עָשְׁקָה לִי עָרְבֵנִי. תָּנָא, בְּהַהוּא יוֹמָא תַּקִּיפָא וּדְחִילוּ דְבַר נָשׁ, כַּד מָטֵי זִמְנֵיהּ לְאִסְתַּלָּקָא מֵעַלְמָא, אַרְבַּע סִטְרִין דְּעַלְמָא קָיְימִין בְּדִינָא תַּקִּיפָא, וּמִתְעָרִין דִּינִין מֵאַרְבַּע סִטְרֵי עָלְמָא. וְאַרְבַּע קִשּׁוּרִין נָצָאן, וּקְטָטוּתָא אִשְׁתַּכַּח בֵּינַיְיהוּ, וּבָעְיָין לְאִתְפְּרָשָׁא כָּל חַד לְסִטְרוֹי. כָּרוֹזָא נָפִיק וּמַכְרְזָא בְּהַהוּא עַלְמָא, וְאִשְׁתְּמַע בְּמָאתָן וְשִׁבְעִין עָלְמִין. אִי זַכָּאָה הוּא, כֻּלְּהוּ עָלְמִין חָדָאן לְקָדָמוּתֵיהּ. וְאִי לָאו, וַוי לְהַהוּא בַּר נָשׁ וּלְחוּלָקֵיהּ. תָּנָא, בְּהַהוּא זִמְנָא דְּכָרוֹזָא כָּרִיז, כְּדֵין נָפַק חַד שַׁלְהוֹבָא מִסְּטַר צָפוֹן, וְאָזְלָא וְאִתּוֹקַד בִּנְהַר דִּינוּר, וּמִתְפָּרְשָׁא לְאַרְבַּע סִטְרֵי עַלְמָא, וְאוֹקִיד נִשְׁמַתְהוֹן דְּחַיָּיבַיָא. וְנָפַק הַהוּא שַׁלְהוֹבָא, וְסָלְקָא וְנָחֲתָא בְּעַלְמָא. וְהַהוּא שַׁלְהוֹבָא מָטָא בְּגַדְפוֹי דְתַרְנְגוֹלָא אוּכְמָא, וּבָטַשׁ בְּגַדְפוֹי, וְקָרֵי בְּפִתְחָא בֵּין תַּרְעֵי. זִמְנָא קַדְמָאָה קָרֵי וְאָמַר, (מלאכי ג׳:י״ט) הִנֵּה יוֹם ה' בָּא בּוֹעֵר כַּתַּנּוּר וְגו'. זִמְנָא תִּנְיָינָא קָרֵי וְאָמַר, (עמוס ד׳:י״ג) כִּי הִנֵּה יוֹצֵר הָרִים וּבוֹרֵא רוּחַ וּמַגִּיד לְאָדָם מַה שֵּׂחוֹ. וְהַהִיא שַׁעֲתָּא, יָתִיב בַּר נָשׁ בְּעוֹבָדוֹי, דְּסָהֲדִין קַמֵּיהּ, וְהוּא אוֹדֵי עֲלַיְיהוּ. זִמְנָא תְּלִיתָאָה, כַּד בָּעְיָין לְאֲפָקָא נִשְׁמָתֵיהּ מִנֵּיהּ, קָרֵי תַּרְנְגוֹלָא וְאָמַר, (ירמיהו י׳:ז׳) מִי לֹא יִירָאֲךָ מֶלֶךְ הַגּוֹיִם כִּי לְךָ יָאָתָה וְגו'. אָמַר רִבִּי יוֹסֵי, תַּרְנְגוֹלָא אוּכְמָא לְמַאי נַפְקָא. אָמַר לֵיהּ רִבִּי יְהוּדָה, כָּל מַה דְּעֲבַד קוּדְשָׁא בְּרִיךְ הוּא בְּאַרְעָא, כֻּלְּהוּ רָמִיז בְּחָכְמָה, בַּר דִּבְנֵי נָשָׁא לָא יָדְעֵי. הֲדָא הוּא דִכְתִיב, (תהילים ק״ד:כ״ד) מָה רַבּוּ מַעֲשֶׂיךָ ה' כֻּלָּם בְּחָכְמָה עָשִׂיתָ מָלְאָה הָאָרֶץ קִנְיָנֶיךָ, וּמִשּׁוּם דְּאִתְעֲבִידוּ בְּחָכְמָה, כֻּלְּהוּ רְמִיזִין בְּחָכְמָה. וְתַרְנְגוֹלָא אוּכְמָא, תָּנִינָן, לֵית דִּינָא שַׁרְיָא אֶלָּא בְּאֲתַר דְּהוּא זִינִיהּ. וְאוּכְמָא מִסִּטְרָא דְּדִינָא קָאָתֵי. וּבְגִין כָּךְ, בְּפַלְגוּת לֵילְיָא מַמָּשׁ, כַּד רוּחָא דְסִטְרָא דְּצָפוֹן אִתְעַר, חַד שַׁלְהוֹבָא נָפִיק, וּבָטַשׁ תְּחוֹת גַּדְפוֹי דְתַרְנְגוֹלָא, וְקָרֵי. וְכָל שֶׁכֵּן בְּתַרְנְגוֹלָא אוּכְמָא, דְּאִתְכַּוֵּון יַתִּיר מֵאַחֲרָא. אוּף הָכָא, בְּשַׁעְתָּא דְּדִינָא דְבַר נָשׁ יִתְעַר, שָׁארֵי וְקָרֵי לֵיהּ, וְלֵית דְּיָדַע לֵיהּ, בַּר הַהוּא בַּר נָשׁ דְּשָׁכִיב. דְּתָנִינָן, בְּשַׁעְתָּא דְּבַר נָשׁ שָׁכִיב, וְדִינָא שַׁרְיָא עֲלֵיהּ לְנַפְקָא מֵהַאי עַלְמָא, אִתּוֹסַף רוּחָא עִלָּאָה בֵּיהּ, מַה דְּלָא הֲוָה בְּיוֹמוֹי. וְכֵיוָן דְּשַׁרְיָא עֲלוֹי וְאִתְדָּבַּק בֵּיהּ, חָמֵי מַה דְּלָא זָכָה בְּיוֹמוֹי, מִשּׁוּם דְּאִתּוֹסַף בֵּיהּ הַהוּא רוּחָא. וְכַד אִתּוֹסַף בֵּיהּ וְחָמָא, כְּדֵין נָפִיק מֵהַאי עַלְמָא, הֲדָא הוּא דִכְתִיב, (תהילים ק״ד:כ״ט) תּוֹסֶף רוּחָם יִגְוָעוּן וְאֶל עֲפָרָם יְשׁוּבוּן. כְּדֵין כְּתִיב, (שמות ל״ג:כ׳) כִּי לֹא יִרְאַנִי הָאָדָם וָחָי, בְּחַיֵּיהוֹן לָא זָכָאן, בְּמִיתַתְהוֹן זָכָאן. תָּאנָא, בְּשַׁעְתָּא דְּבַר נָשׁ מִית, אִתְיְהִיב לֵיהּ רְשׁוּתָא לְמֶחֱמֵי, וְחָמֵי גַבֵּיהּ קְרִיבוֹי וְחַבְרוֹי מֵהַהוּא עָלְמָא, וְאִשְׁתְּמוֹדַע לְהוּ. וְכֻלְּהוּ גְּלִיפִין בְּדִיוּקְנֵיהוֹן כְּמָה דְּהֲווּ בְּהַאי עַלְמָא. אִי זַכָּאָה הַהוּא בַּר נָשׁ, כֻּלְּהוּ חָדָאן קַמֵּיהּ, וּמַקְדְּמֵי לֵיהּ שְׁלָם. וְאִי זַכָּאָה לָא הֲוֵי, לָא אִשְׁתְּמוֹדְעָן גַּבֵּיהּ, בַּר מֵאִינוּן חַיָּיבַיָא, דְּטָרְדִין לוֹן בְּכָל יוֹמָא בַּגֵּיהִנָּם. וְכֻלְּהוּ עֲצִיבִין, וּפָתְחִין בְּוַוי וּמְסַיְּימִין בְּוַוי. וְסָלִיק עֵינוֹי, וְחָמָא לוֹן כְּטִיסָא דְּמִסְתַּלְּקָא מִן נוּרָא, אוּף הָכִי, הוּא פָּתַח, וַוי. תַּנְיָא, בְּשַׁעְתָּא דְּנָפַק נִשְׁמָתֵיהּ דְּבַר נָשׁ, אָזְלִין כֻּלְּהוּ קְרִיבוֹי וְחַבְרוֹי דְּהַהוּא עַלְמָא עִם נִשְׁמָתֵיהּ, וּמַחְזְיָין לֵיהּ אַתְרָא דְעִדּוּנָא, וְאַתְרָא דְּעוֹנָשָׁא. אִי זַכָּאָה הֲוִי, חָמֵי דוּכְתֵּיהּ, וְסָלִיק וְיָתִיב, וְאִתְעֲדַן בְּעִדּוּנָא עִלָּאָה דְּהַהוּא עָלְמָא. וְאִי לָא הֲוֵי זַכָּאָה, אִשְׁתְּאָרַת הַהִיא נִשְׁמָתָא בְּהַאי עַלְמָא, עַד דְּאִטָמִיר גּוּפָא בְּאַרְעָא. כֵּיוָן דְּאִטָמַר, כַּמָּה גַרְדִּינִין דְּנִמּוּסִין אַחֲדָן בֵּיהּ, עַד דְּמָטָא לְדוּמָ\"ה, וְעָאלִין לֵיהּ בְּמָדוֹרוֹי דְּגֵיהִנֹּם. אָמַר רִבִּי יְהוּדָה, כָּל ז' יוֹמִין, נִשְׁמָתָא אָזְלָא מִבֵּיתֵיהּ לְקִבְרֵיהּ, וּמִקִּבְרֵיהּ לְבֵיתֵיהּ, וְאִתְאַבָּלַת עֲלוֹי דְגוּפָא. דִּכְתִיב, (איוב י״ד:כ״ב) אַךְ בְּשָׂרוֹ עָלָיו יִכְאָב וְנַפְשׁוֹ עָלָיו תֶּאֱבָל. אָזְלָא וְיָתְבָא בְּבֵיתֵיהּ, חָמֵי לְכֻלְּהוּ עֲצִיבִין וּמִתְאַבְּלָא. תָּנָא, בָּתַר ז' יוֹמִין, גּוּפָא הֲוֵי כְּמָה דְּהֲוָה, וְנִשְׁמָתֵיהּ עָאלַת לְדוּכְתָּא, עָאלַת לִמְעַרְתָּא דְכָפֵלְתָּא, חָמַאת מַה דְּחָמַאת, וְעָאלַת לְאֲתַר דְּעָאלַת, עַד דְּמָטַת לְגַּן עֵדֶן, וְעַרְעָת לִכְרוּבִים, וְשָׁנַן דְּחַרְבָּא דִּי בְּגַּן עֵדֶן דִּלְתַתָּא. אִי זַכָּאָה הוּא דְּתֵיעוּל, עָאלַת. תָּאנָא, אַרְבַּע סַמְכִין זְמִינִין, וְחַד דִּיוּקְנָא דְגוּפָא בִּידַיְיהוּ, (שמות ר\"י ע\"א) מִתְלַבְּשָׁא בֵּיהּ בְּחֶדְוָותָא וְיָתִיבַת בְּהַהוּא מָדוֹרָא דְּגַּן עֵדֶן דִּלְתַתָּא, עַד זִמְנָא דְאִתְגְּזַר עֲלָהּ. לְבָתַר כְּרוֹזָא קָרֵי. וְעַמּוּדָא דִתְלַת גְּוָונֵי אִזְדַּמַּן, וְהַהוּא עַמּוּדָא אִתְקְרֵי, מְכוֹן הַר צִיּוֹן דִּכְתִיב, (ישעיהו ד׳:ה׳) וּבָרָא ה' עַל מְכוֹן הַר צִיּוֹן וְעַל מִקְרָאֶיהָ עָנָן יוֹמָם וְעָשָׁן וְגו'. סָלְקָא בְּהַהוּא עַמּוּדָא לְפִתְחָא דְצֶדֶק, דְּצִיּוֹן וִירוּשָׁלַם בֵּיהּ. אִי זָכֵי לְסַלְקָא יַתִּיר, טַב חוּלָקֵיהּ וְעַדְבֵיהּ, לְאִתְדַּבְּקָא בְּגוֹ גוּפָא דְמַלְכָּא. וְאִי לָא זָכֵי לְסַלְּקָא יַתִּיר, כְּתִיב, (ישעיהו ד׳:ג׳) וְהָיָה הַנִּשְׁאָר בְּצִיּוֹן וְהַנּוֹתָר בִּירוּשָׁלַם קָדוֹשׁ יֵאָמֶר לוֹ. וְאִי זָכֵי לְסַלְקָא יַתִּיר, זַכָּאָה הוּא. דְּזָכֵי לִיקָרָא דְמַלְכָּא, וּלְאִתְעַדְּנָא בְּעִדּוּנָא עִלָּאָה, דִּלְעֵילָא מֵאֲתַר דְּאִקְרֵי שָׁמַיִם. דִּכְתִיב, (ישעיהו נ״ח:י״ד) אָז תִּתְעַנֵּג עַל ה', עַל ה' דַּיְיקָא. זַכָּאָה חוּלָקֵיהּ דְּמַאן דְּזָכֵי לְחֶסֶד דָּא, דִּכְתִיב, (תהילים ק״ח:ה׳) כִּי גָדוֹל מֵעַל שָׁמַיִם חַסְדֶּךָ. וְכִי עַל הַשָּׁמַיִם הוּא, וְהָא כְּתִיב, (תהילים נ״ז:י״א) כִּי גָדוֹל עַד שָׁמַיִם חַסְדֶּךָ. אָמַר רִבִּי יוֹסֵי, אִית חֶסֶד, וְאִית חֶסֶד. חֶסֶד עִלָּאָה, וְחֶסֶד תַּתָּאָה. חֶסֶד עִלָּאָה מֵעַל שָׁמַיִם הוּא. חֶסֶד תַּתָּאָה, הוּא דִכְתִיב, (ישעיהו נ״ה:ג׳) חַסְדֵּי דָוִד הַנֶּאֱמָנִים, וּבְהַנֵּי כְּתִיב עַד שָׁמַיִם."
    },
    {
      "id": "Zohar_Vayechi.22.1",
      "book": "Zohar",
      "parsha": "Vayechi",
      "chapter": 22,
      "text_en": "R. Isaac once questioned R. Simeon with regard to the verse, “a joyful mother of children”, saying: ‘I know what is meant by the mother, but who are the children?’ R. Simeon answered: ‘There are two children to God, one male and one female. The male he gave to Jacob, as it is written: “Israel is my son, my firstborn” (Ex. 4, 22). The female he gave to Abraham. The mother sits on the young and gives them suck; whence the precept, “Thou shalt not take the mother with the young.” Our teachers have said: “A man should beware of sinfulness below lest thereby the mother should be parted from the children.” But when men repent and act virtuously then the mother returns and shelters the young, and this is called “repentance” (, lit. returning). Then, too, it can be said, “the mother of the children is joyful”. Hence a man should not cease from propagating his kind till he has a son and a daughter.’ R. Isaac was not yet satisfied. ‘The righteous’, he said, ‘desire no more than to “behold the pleasantness of the Lord” (Ps. 27, 4).’ R. Simeon answered: ‘It is all one, since this pleasantness comes from the Holy Ancient One to this heaven, and the desire of the righteous is fixed on that.’",
      "text_he": "תַּנְיָא, אָמַר רִבִּי יִצְחָק, כְּתִיב, (תהילים קי״ג:ט׳) אֵם הַבָּנִים שְׂמֵחָה הַלְּלוּיָה, אִמָּא יְדִיעָא, הַבָּנִים מַאן אִינוּן. אָמַר רִבִּי שִׁמְעוֹן, הָא תָּנִינָן, תְּרֵין בְּנִין אִית לְקוּדְשָׁא בְּרִיךְ הוּא, חַד דְּכַר וְחַד נוּקְבָא. דְּכַר, יַהֲבֵיהּ לְיַעֲקֹב, דִּכְתִיב, (שמות ד) בְּנִי בְּכוֹרִי יִשְׂרָאֵל, וּכְתִיב, (ישעיהו מ״ט:ג׳) יִשְׂרָאֵל אֲשֶׁר בְּךָ אֶתְפָּאֵר. בַּת, יַהֲבָהּ לְאַבְרָהָם, דִּכְתִיב, (בראשית כ״ד:א׳) וַה' בֵּרַךְ אֶת אַבְרָהָם בַּכֹּל, בַּת הָיְתָה לוֹ לְאַבְרָהָם, וּבַכֹּל שְׁמָה. וְאִמָא רְבִיעָא עֲלַיְיהוּ, דְּיָנְקָא לְהוּ, וְעַל הַאי כְּתִיב, (דברים קד) לא תִקַּח הָאֵם עַל הַבָּנִים. וְתָנִינָן, לָא יַסְגֵּי בַּר נָשׁ חוֹבוֹי לְתַתָּא, בְּגִין דְּיִסְתַּלַּק אִמָּא מֵעַל בְּנִין. וּכְתִיב, (ויקרא י״ח:ז׳) אִמְּךָ הִיא לא תְגַלֵּה עֶרְוָתָהּ, וַוי לְמַאן דְּגָלֵי עֶרְיָיתָא. וְכַד תָּיְיבִין בְּנֵי עַלְמָא, וְאַסְגִּין בִּזְכוּתָא קַמֵּי קוּדְשָׁא בְּרִיךְ הוּא, וְאִמָּא תָבַת וְכַסְיָא עַל בְּנִין, כְּדֵין אִתְקְרֵי תְּשׁוּבָה. מַאי תְּשׁוּבָה. דָּא תְּשׁוּבָה דְאִמָּא, דְּתָבַת בְּקִיּוּמָהָא, וּכְדֵין (שמות פ\"ג ע\"א) כְּתִיב, (תהילים קי״ג:ט׳) אֵם הַבָּנִים שְׂמֵחָה, אֵם הַבָּנִים וַדַּאי. וְעַל דָּא, לָא לִפָּטַר אִינִישׁ מִפְּרִיָּה וּרְבִיָּה, עַד דְּאוֹלִיד בֵּן וּבַת. תַּנְיָא אָמַר רִבִּי יִצְחָק, כְּתִיב, (תהילים כ״ז:ד׳) לַחֲזוֹת בְּנֹעַם ה' וּלְבַקֵּר בְּהֵיכָלוֹ, תִּיאוּבְתָּא דְצַדִּיקַיָא לְמֶחֱמֵי דָא, (ז\"ח ל\"ג נעם ה') וְאַתְּ אֲמַרְתְּ עַל ה'. אָמַר רִבִּי שִׁמְעוֹן, כֹּלָּא חַד. מַשְׁמַע דִּכְתִיב נֹעַם ה', דְּאַתְיָא מֵעַתִּיקָא קַדִּישָׁא לְהַאי שָׁמַיִם. וְתִיאוּבְתָּא דְצַדִּיקַיָא כָּךְ הוּא וַדַּאי, וְעַל הַשָּׁמַיִם כְּתִיב, אָז תִּתְעַנֵּג עַל ה'. זַכָּאָה חוּלָקֵיהּ מַאן דְּזָכֵי. וַדַּאי זְעִירִין אִינוּן."
    }
  ]
}